[
    {
        "segment_tag": "UNB",
        "syntax": {
            "identifier-0001": "UNOC",
            "version-0002": "3"
        },
        "sender": {
            "id-0004": "9905048000007",
            "qualifier-0007": "500"
        },
        "receiver": {
            "id-0010": "9985046000001",
            "qualifier-0007": "500"
        },
        "datetime": {
            "date-0017": "250108",
            "time-0019": "1822"
        },
        "reference-0020": "CS0000000GA0FI",
        "application_ref-0026": "TL"
    },
    {
        "segment_tag": "UNH",
        "message_reference-0062": "1",
        "message_type": {
            "message_type_id-0065": "MSCONS",
            "message_version-0052": "D",
            "message_release-0054": "04B",
            "controlling_agency-0051": "UN",
            "association_code-0057": "2.4c",
            "common_access_ref-0068": null
        },
        "transmission": {
            "sequence_number-0070": null,
            "sequence_status-0073": null
        }
    },
    {
        "segment_tag": "BGM",
        "document_code-1001": "Z48",
        "document_name-1001": "Lastgang Marktlokation, Tranche",
        "document_number-1004": "CS0000000GA0FI-1",
        "message_function_code-1225": "9"
    },
    {
        "segment_tag": "DTM",
        "function_code-2005": "137",
        "value-2380": "202501081822+00",
        "format_code-2379": "303"
    },
    {
        "segment_tag": "RFF",
        "qualifier-1153": "Z13",
        "identifier-1154": "13025"
    },
    {
        "segment_tag": "NAD",
        "party_qualifier-3035": "MS",
        "party_id-3039": "9905048000007",
        "code_list-1131": "",
        "resp_agency-3055": "293"
    },
    {
        "segment_tag": "NAD",
        "party_qualifier-3035": "MR",
        "party_id-3039": "9985046000001",
        "code_list-1131": "",
        "resp_agency-3055": "293"
    },
    {
        "segment_tag": "UNS",
        "section_id-0081": "D"
    },
    {
        "segment_tag": "NAD",
        "party_qualifier-3035": "DP",
        "party_id-3039": null,
        "code_list-1131": null,
        "resp_agency-3055": null
    },
    {
        "segment_tag": "LOC",
        "location_qualifier-3227": "172",
        "location_code-3225": "50120962218",
        "first_related_code-3223": null
    },
    {
        "segment_tag": "DTM",
        "function_code-2005": "163",
        "value-2380": "202412242300+00",
        "format_code-2379": "303"
    },
    {
        "segment_tag": "DTM",
        "function_code-2005": "164",
        "value-2380": "202412252300+00",
        "format_code-2379": "303"
    },
    {
        "segment_tag": "LIN",
        "line_item_number-1082": "1"
    },
    {
        "segment_tag": "PIA",
        "qualifier-4347": "5",
        "product_number-7140": "1-1:1.29.0",
        "product_type-7143": "SRW"
    },
    {
        "segment_tag": "QTY",
        "quantity_qualifier-6063": "220",
        "quantity_value-6060": "1,857",
        "quantity_unit-6411": null
    },
    {
        "segment_tag": "DTM",
        "function_code-2005": "163",
        "value-2380": "202412242300+00",
        "format_code-2379": "303"
    },
    {
        "segment_tag": "DTM",
        "function_code-2005": "164",
        "value-2380": "202412242315+00",
        "format_code-2379": "303"
    },
    {
        "segment_tag": "QTY",
        "quantity_qualifier-6063": "220",
        "quantity_value-6060": "1,146",
        "quantity_unit-6411": null
    },
    {
        "segment_tag": "DTM",
        "function_code-2005": "163",
        "value-2380": "202412242315+00",
        "format_code-2379": "303"
    },
    {
        "segment_tag": "DTM",
        "function_code-2005": "164",
        "value-2380": "202412242330+00",
        "format_code-2379": "303"
    },
    {
        "segment_tag": "QTY",
        "quantity_qualifier-6063": "220",
        "quantity_value-6060": "1,141",
        "quantity_unit-6411": null
    },
    {
        "segment_tag": "DTM",
        "function_code-2005": "163",
        "value-2380": "202412242330+00",
        "format_code-2379": "303"
    },
    {
        "segment_tag": "DTM",
        "function_code-2005": "164",
        "value-2380": "202412242345+00",
        "format_code-2379": "303"
    },
    {
        "segment_tag": "QTY",
        "quantity_qualifier-6063": "220",
        "quantity_value-6060": "0,763",
        "quantity_unit-6411": null
    },
    {
        "segment_tag": "DTM",
        "function_code-2005": "163",
        "value-2380": "202412242345+00",
        "format_code-2379": "303"
    },
    {
        "segment_tag": "DTM",
        "function_code-2005": "164",
        "value-2380": "202412250000+00",
        "format_code-2379": "303"
    },
    {
        "segment_tag": "QTY",
        "quantity_qualifier-6063": "220",
        "quantity_value-6060": "1,062",
        "quantity_unit-6411": null
    },
    {
        "segment_tag": "DTM",
        "function_code-2005": "163",
        "value-2380": "202412250000+00",
        "format_code-2379": "303"
    },
    {
        "segment_tag": "DTM",
        "function_code-2005": "164",
        "value-2380": "202412250015+00",
        "format_code-2379": "303"
    },
    {
        "segment_tag": "QTY",
        "quantity_qualifier-6063": "220",
        "quantity_value-6060": "1,471",
        "quantity_unit-6411": null
    },
    {
        "segment_tag": "DTM",
        "function_code-2005": "163",
        "value-2380": "202412250015+00",
        "format_code-2379": "303"
    },
    {
        "segment_tag": "DTM",
        "function_code-2005": "164",
        "value-2380": "202412250030+00",
        "format_code-2379": "303"
    },
    {
        "segment_tag": "QTY",
        "quantity_qualifier-6063": "220",
        "quantity_value-6060": "1,626",
        "quantity_unit-6411": null
    },
    {
        "segment_tag": "DTM",
        "function_code-2005": "163",
        "value-2380": "202412250030+00",
        "format_code-2379": "303"
    },
    {
        "segment_tag": "DTM",
        "function_code-2005": "164",
        "value-2380": "202412250045+00",
        "format_code-2379": "303"
    },
    {
        "segment_tag": "QTY",
        "quantity_qualifier-6063": "220",
        "quantity_value-6060": "1,643",
        "quantity_unit-6411": null
    },
    {
        "segment_tag": "DTM",
        "function_code-2005": "163",
        "value-2380": "202412250045+00",
        "format_code-2379": "303"
    },
    {
        "segment_tag": "DTM",
        "function_code-2005": "164",
        "value-2380": "202412250100+00",
        "format_code-2379": "303"
    },
    {
        "segment_tag": "QTY",
        "quantity_qualifier-6063": "220",
        "quantity_value-6060": "1,711",
        "quantity_unit-6411": null
    },
    {
        "segment_tag": "DTM",
        "function_code-2005": "163",
        "value-2380": "202412250100+00",
        "format_code-2379": "303"
    },
    {
        "segment_tag": "DTM",
        "function_code-2005": "164",
        "value-2380": "202412250115+00",
        "format_code-2379": "303"
    },
    {
        "segment_tag": "QTY",
        "quantity_qualifier-6063": "220",
        "quantity_value-6060": "1,998",
        "quantity_unit-6411": null
    },
    {
        "segment_tag": "DTM",
        "function_code-2005": "163",
        "value-2380": "202412250115+00",
        "format_code-2379": "303"
    },
    {
        "segment_tag": "DTM",
        "function_code-2005": "164",
        "value-2380": "202412250130+00",
        "format_code-2379": "303"
    },
    {
        "segment_tag": "QTY",
        "quantity_qualifier-6063": "220",
        "quantity_value-6060": "2,606",
        "quantity_unit-6411": null
    },
    {
        "segment_tag": "DTM",
        "function_code-2005": "163",
        "value-2380": "202412250130+00",
        "format_code-2379": "303"
    },
    {
        "segment_tag": "DTM",
        "function_code-2005": "164",
        "value-2380": "202412250145+00",
        "format_code-2379": "303"
    },
    {
        "segment_tag": "QTY",
        "quantity_qualifier-6063": "220",
        "quantity_value-6060": "1,997",
        "quantity_unit-6411": null
    },
    {
        "segment_tag": "DTM",
        "function_code-2005": "163",
        "value-2380": "202412250145+00",
        "format_code-2379": "303"
    },
    {
        "segment_tag": "DTM",
        "function_code-2005": "164",
        "value-2380": "202412250200+00",
        "format_code-2379": "303"
    },
    {
        "segment_tag": "QTY",
        "quantity_qualifier-6063": "220",
        "quantity_value-6060": "1,878",
        "quantity_unit-6411": null
    },
    {
        "segment_tag": "DTM",
        "function_code-2005": "163",
        "value-2380": "202412250200+00",
        "format_code-2379": "303"
    },
    {
        "segment_tag": "DTM",
        "function_code-2005": "164",
        "value-2380": "202412250215+00",
        "format_code-2379": "303"
    },
    {
        "segment_tag": "QTY",
        "quantity_qualifier-6063": "220",
        "quantity_value-6060": "1,852",
        "quantity_unit-6411": null
    },
    {
        "segment_tag": "DTM",
        "function_code-2005": "163",
        "value-2380": "202412250215+00",
        "format_code-2379": "303"
    },
    {
        "segment_tag": "DTM",
        "function_code-2005": "164",
        "value-2380": "202412250230+00",
        "format_code-2379": "303"
    },
    {
        "segment_tag": "QTY",
        "quantity_qualifier-6063": "220",
        "quantity_value-6060": "1,475",
        "quantity_unit-6411": null
    },
    {
        "segment_tag": "DTM",
        "function_code-2005": "163",
        "value-2380": "202412250230+00",
        "format_code-2379": "303"
    },
    {
        "segment_tag": "DTM",
        "function_code-2005": "164",
        "value-2380": "202412250245+00",
        "format_code-2379": "303"
    },
    {
        "segment_tag": "QTY",
        "quantity_qualifier-6063": "220",
        "quantity_value-6060": "1,245",
        "quantity_unit-6411": null
    },
    {
        "segment_tag": "DTM",
        "function_code-2005": "163",
        "value-2380": "202412250245+00",
        "format_code-2379": "303"
    },
    {
        "segment_tag": "DTM",
        "function_code-2005": "164",
        "value-2380": "202412250300+00",
        "format_code-2379": "303"
    },
    {
        "segment_tag": "QTY",
        "quantity_qualifier-6063": "220",
        "quantity_value-6060": "1,615",
        "quantity_unit-6411": null
    },
    {
        "segment_tag": "DTM",
        "function_code-2005": "163",
        "value-2380": "202412250300+00",
        "format_code-2379": "303"
    },
    {
        "segment_tag": "DTM",
        "function_code-2005": "164",
        "value-2380": "202412250315+00",
        "format_code-2379": "303"
    },
    {
        "segment_tag": "QTY",
        "quantity_qualifier-6063": "220",
        "quantity_value-6060": "1,591",
        "quantity_unit-6411": null
    },
    {
        "segment_tag": "DTM",
        "function_code-2005": "163",
        "value-2380": "202412250315+00",
        "format_code-2379": "303"
    },
    {
        "segment_tag": "DTM",
        "function_code-2005": "164",
        "value-2380": "202412250330+00",
        "format_code-2379": "303"
    },
    {
        "segment_tag": "QTY",
        "quantity_qualifier-6063": "220",
        "quantity_value-6060": "1,585",
        "quantity_unit-6411": null
    },
    {
        "segment_tag": "DTM",
        "function_code-2005": "163",
        "value-2380": "202412250330+00",
        "format_code-2379": "303"
    },
    {
        "segment_tag": "DTM",
        "function_code-2005": "164",
        "value-2380": "202412250345+00",
        "format_code-2379": "303"
    },
    {
        "segment_tag": "QTY",
        "quantity_qualifier-6063": "220",
        "quantity_value-6060": "2,201",
        "quantity_unit-6411": null
    },
    {
        "segment_tag": "DTM",
        "function_code-2005": "163",
        "value-2380": "202412250345+00",
        "format_code-2379": "303"
    },
    {
        "segment_tag": "DTM",
        "function_code-2005": "164",
        "value-2380": "202412250400+00",
        "format_code-2379": "303"
    },
    {
        "segment_tag": "QTY",
        "quantity_qualifier-6063": "220",
        "quantity_value-6060": "3,221",
        "quantity_unit-6411": null
    },
    {
        "segment_tag": "DTM",
        "function_code-2005": "163",
        "value-2380": "202412250400+00",
        "format_code-2379": "303"
    },
    {
        "segment_tag": "DTM",
        "function_code-2005": "164",
        "value-2380": "202412250415+00",
        "format_code-2379": "303"
    },
    {
        "segment_tag": "QTY",
        "quantity_qualifier-6063": "220",
        "quantity_value-6060": "2,626",
        "quantity_unit-6411": null
    },
    {
        "segment_tag": "DTM",
        "function_code-2005": "163",
        "value-2380": "202412250415+00",
        "format_code-2379": "303"
    },
    {
        "segment_tag": "DTM",
        "function_code-2005": "164",
        "value-2380": "202412250430+00",
        "format_code-2379": "303"
    },
    {
        "segment_tag": "QTY",
        "quantity_qualifier-6063": "220",
        "quantity_value-6060": "1,609",
        "quantity_unit-6411": null
    },
    {
        "segment_tag": "DTM",
        "function_code-2005": "163",
        "value-2380": "202412250430+00",
        "format_code-2379": "303"
    },
    {
        "segment_tag": "DTM",
        "function_code-2005": "164",
        "value-2380": "202412250445+00",
        "format_code-2379": "303"
    },
    {
        "segment_tag": "QTY",
        "quantity_qualifier-6063": "220",
        "quantity_value-6060": "1,428",
        "quantity_unit-6411": null
    },
    {
        "segment_tag": "DTM",
        "function_code-2005": "163",
        "value-2380": "202412250445+00",
        "format_code-2379": "303"
    },
    {
        "segment_tag": "DTM",
        "function_code-2005": "164",
        "value-2380": "202412250500+00",
        "format_code-2379": "303"
    },
    {
        "segment_tag": "QTY",
        "quantity_qualifier-6063": "220",
        "quantity_value-6060": "1,188",
        "quantity_unit-6411": null
    },
    {
        "segment_tag": "DTM",
        "function_code-2005": "163",
        "value-2380": "202412250500+00",
        "format_code-2379": "303"
    },
    {
        "segment_tag": "DTM",
        "function_code-2005": "164",
        "value-2380": "202412250515+00",
        "format_code-2379": "303"
    },
    {
        "segment_tag": "QTY",
        "quantity_qualifier-6063": "220",
        "quantity_value-6060": "3,804",
        "quantity_unit-6411": null
    },
    {
        "segment_tag": "DTM",
        "function_code-2005": "163",
        "value-2380": "202412250515+00",
        "format_code-2379": "303"
    },
    {
        "segment_tag": "DTM",
        "function_code-2005": "164",
        "value-2380": "202412250530+00",
        "format_code-2379": "303"
    },
    {
        "segment_tag": "QTY",
        "quantity_qualifier-6063": "220",
        "quantity_value-6060": "1,913",
        "quantity_unit-6411": null
    },
    {
        "segment_tag": "DTM",
        "function_code-2005": "163",
        "value-2380": "202412250530+00",
        "format_code-2379": "303"
    },
    {
        "segment_tag": "DTM",
        "function_code-2005": "164",
        "value-2380": "202412250545+00",
        "format_code-2379": "303"
    },
    {
        "segment_tag": "QTY",
        "quantity_qualifier-6063": "67",
        "quantity_value-6060": "1,654",
        "quantity_unit-6411": null
    },
    {
        "segment_tag": "DTM",
        "function_code-2005": "163",
        "value-2380": "202412250545+00",
        "format_code-2379": "303"
    },
    {
        "segment_tag": "DTM",
        "function_code-2005": "164",
        "value-2380": "202412250600+00",
        "format_code-2379": "303"
    },
    {
        "segment_tag": "STS",
        "status_category_code-9015": "Z32",
        "status_reason_code-9013": "ZJ2"
    },
    {
        "segment_tag": "STS",
        "status_category_code-9015": "Z34",
        "status_reason_code-9013": "ZB0"
    },
    {
        "segment_tag": "STS",
        "status_category_code-9015": "Z40",
        "status_reason_code-9013": "ZB0"
    },
    {
        "segment_tag": "QTY",
        "quantity_qualifier-6063": "67",
        "quantity_value-6060": "1,654",
        "quantity_unit-6411": null
    },
    {
        "segment_tag": "DTM",
        "function_code-2005": "163",
        "value-2380": "202412250600+00",
        "format_code-2379": "303"
    },
    {
        "segment_tag": "DTM",
        "function_code-2005": "164",
        "value-2380": "202412250615+00",
        "format_code-2379": "303"
    },
    {
        "segment_tag": "STS",
        "status_category_code-9015": "Z32",
        "status_reason_code-9013": "ZJ2"
    },
    {
        "segment_tag": "STS",
        "status_category_code-9015": "Z34",
        "status_reason_code-9013": "ZB0"
    },
    {
        "segment_tag": "STS",
        "status_category_code-9015": "Z40",
        "status_reason_code-9013": "ZB0"
    },
    {
        "segment_tag": "QTY",
        "quantity_qualifier-6063": "220",
        "quantity_value-6060": "1,577",
        "quantity_unit-6411": null
    },
    {
        "segment_tag": "DTM",
        "function_code-2005": "163",
        "value-2380": "202412250615+00",
        "format_code-2379": "303"
    },
    {
        "segment_tag": "DTM",
        "function_code-2005": "164",
        "value-2380": "202412250630+00",
        "format_code-2379": "303"
    },
    {
        "segment_tag": "QTY",
        "quantity_qualifier-6063": "220",
        "quantity_value-6060": "1,833",
        "quantity_unit-6411": null
    },
    {
        "segment_tag": "DTM",
        "function_code-2005": "163",
        "value-2380": "202412250630+00",
        "format_code-2379": "303"
    },
    {
        "segment_tag": "DTM",
        "function_code-2005": "164",
        "value-2380": "202412250645+00",
        "format_code-2379": "303"
    },
    {
        "segment_tag": "QTY",
        "quantity_qualifier-6063": "220",
        "quantity_value-6060": "2,162",
        "quantity_unit-6411": null
    },
    {
        "segment_tag": "DTM",
        "function_code-2005": "163",
        "value-2380": "202412250645+00",
        "format_code-2379": "303"
    },
    {
        "segment_tag": "DTM",
        "function_code-2005": "164",
        "value-2380": "202412250700+00",
        "format_code-2379": "303"
    },
    {
        "segment_tag": "QTY",
        "quantity_qualifier-6063": "220",
        "quantity_value-6060": "2,196",
        "quantity_unit-6411": null
    },
    {
        "segment_tag": "DTM",
        "function_code-2005": "163",
        "value-2380": "202412250700+00",
        "format_code-2379": "303"
    },
    {
        "segment_tag": "DTM",
        "function_code-2005": "164",
        "value-2380": "202412250715+00",
        "format_code-2379": "303"
    },
    {
        "segment_tag": "QTY",
        "quantity_qualifier-6063": "220",
        "quantity_value-6060": "2,176",
        "quantity_unit-6411": null
    },
    {
        "segment_tag": "DTM",
        "function_code-2005": "163",
        "value-2380": "202412250715+00",
        "format_code-2379": "303"
    },
    {
        "segment_tag": "DTM",
        "function_code-2005": "164",
        "value-2380": "202412250730+00",
        "format_code-2379": "303"
    },
    {
        "segment_tag": "QTY",
        "quantity_qualifier-6063": "220",
        "quantity_value-6060": "1,666",
        "quantity_unit-6411": null
    },
    {
        "segment_tag": "DTM",
        "function_code-2005": "163",
        "value-2380": "202412250730+00",
        "format_code-2379": "303"
    },
    {
        "segment_tag": "DTM",
        "function_code-2005": "164",
        "value-2380": "202412250745+00",
        "format_code-2379": "303"
    },
    {
        "segment_tag": "QTY",
        "quantity_qualifier-6063": "220",
        "quantity_value-6060": "1,218",
        "quantity_unit-6411": null
    },
    {
        "segment_tag": "DTM",
        "function_code-2005": "163",
        "value-2380": "202412250745+00",
        "format_code-2379": "303"
    },
    {
        "segment_tag": "DTM",
        "function_code-2005": "164",
        "value-2380": "202412250800+00",
        "format_code-2379": "303"
    },
    {
        "segment_tag": "QTY",
        "quantity_qualifier-6063": "220",
        "quantity_value-6060": "1,111",
        "quantity_unit-6411": null
    },
    {
        "segment_tag": "DTM",
        "function_code-2005": "163",
        "value-2380": "202412250800+00",
        "format_code-2379": "303"
    },
    {
        "segment_tag": "DTM",
        "function_code-2005": "164",
        "value-2380": "202412250815+00",
        "format_code-2379": "303"
    },
    {
        "segment_tag": "QTY",
        "quantity_qualifier-6063": "220",
        "quantity_value-6060": "1,18",
        "quantity_unit-6411": null
    },
    {
        "segment_tag": "DTM",
        "function_code-2005": "163",
        "value-2380": "202412250815+00",
        "format_code-2379": "303"
    },
    {
        "segment_tag": "DTM",
        "function_code-2005": "164",
        "value-2380": "202412250830+00",
        "format_code-2379": "303"
    },
    {
        "segment_tag": "QTY",
        "quantity_qualifier-6063": "220",
        "quantity_value-6060": "0,058",
        "quantity_unit-6411": null
    },
    {
        "segment_tag": "DTM",
        "function_code-2005": "163",
        "value-2380": "202412250830+00",
        "format_code-2379": "303"
    },
    {
        "segment_tag": "DTM",
        "function_code-2005": "164",
        "value-2380": "202412250845+00",
        "format_code-2379": "303"
    },
    {
        "segment_tag": "QTY",
        "quantity_qualifier-6063": "220",
        "quantity_value-6060": "0,039",
        "quantity_unit-6411": null
    },
    {
        "segment_tag": "DTM",
        "function_code-2005": "163",
        "value-2380": "202412250845+00",
        "format_code-2379": "303"
    },
    {
        "segment_tag": "DTM",
        "function_code-2005": "164",
        "value-2380": "202412250900+00",
        "format_code-2379": "303"
    },
    {
        "segment_tag": "QTY",
        "quantity_qualifier-6063": "220",
        "quantity_value-6060": "0,041",
        "quantity_unit-6411": null
    },
    {
        "segment_tag": "DTM",
        "function_code-2005": "163",
        "value-2380": "202412250900+00",
        "format_code-2379": "303"
    },
    {
        "segment_tag": "DTM",
        "function_code-2005": "164",
        "value-2380": "202412250915+00",
        "format_code-2379": "303"
    },
    {
        "segment_tag": "QTY",
        "quantity_qualifier-6063": "220",
        "quantity_value-6060": "0,04",
        "quantity_unit-6411": null
    },
    {
        "segment_tag": "DTM",
        "function_code-2005": "163",
        "value-2380": "202412250915+00",
        "format_code-2379": "303"
    },
    {
        "segment_tag": "DTM",
        "function_code-2005": "164",
        "value-2380": "202412250930+00",
        "format_code-2379": "303"
    },
    {
        "segment_tag": "QTY",
        "quantity_qualifier-6063": "220",
        "quantity_value-6060": "0,082",
        "quantity_unit-6411": null
    },
    {
        "segment_tag": "DTM",
        "function_code-2005": "163",
        "value-2380": "202412250930+00",
        "format_code-2379": "303"
    },
    {
        "segment_tag": "DTM",
        "function_code-2005": "164",
        "value-2380": "202412250945+00",
        "format_code-2379": "303"
    },
    {
        "segment_tag": "QTY",
        "quantity_qualifier-6063": "220",
        "quantity_value-6060": "0,058",
        "quantity_unit-6411": null
    },
    {
        "segment_tag": "DTM",
        "function_code-2005": "163",
        "value-2380": "202412250945+00",
        "format_code-2379": "303"
    },
    {
        "segment_tag": "DTM",
        "function_code-2005": "164",
        "value-2380": "202412251000+00",
        "format_code-2379": "303"
    },
    {
        "segment_tag": "QTY",
        "quantity_qualifier-6063": "220",
        "quantity_value-6060": "0,045",
        "quantity_unit-6411": null
    },
    {
        "segment_tag": "DTM",
        "function_code-2005": "163",
        "value-2380": "202412251000+00",
        "format_code-2379": "303"
    },
    {
        "segment_tag": "DTM",
        "function_code-2005": "164",
        "value-2380": "202412251015+00",
        "format_code-2379": "303"
    },
    {
        "segment_tag": "QTY",
        "quantity_qualifier-6063": "220",
        "quantity_value-6060": "0,063",
        "quantity_unit-6411": null
    },
    {
        "segment_tag": "DTM",
        "function_code-2005": "163",
        "value-2380": "202412251015+00",
        "format_code-2379": "303"
    },
    {
        "segment_tag": "DTM",
        "function_code-2005": "164",
        "value-2380": "202412251030+00",
        "format_code-2379": "303"
    },
    {
        "segment_tag": "QTY",
        "quantity_qualifier-6063": "220",
        "quantity_value-6060": "0,048",
        "quantity_unit-6411": null
    },
    {
        "segment_tag": "DTM",
        "function_code-2005": "163",
        "value-2380": "202412251030+00",
        "format_code-2379": "303"
    },
    {
        "segment_tag": "DTM",
        "function_code-2005": "164",
        "value-2380": "202412251045+00",
        "format_code-2379": "303"
    },
    {
        "segment_tag": "QTY",
        "quantity_qualifier-6063": "220",
        "quantity_value-6060": "0,038",
        "quantity_unit-6411": null
    },
    {
        "segment_tag": "DTM",
        "function_code-2005": "163",
        "value-2380": "202412251045+00",
        "format_code-2379": "303"
    },
    {
        "segment_tag": "DTM",
        "function_code-2005": "164",
        "value-2380": "202412251100+00",
        "format_code-2379": "303"
    },
    {
        "segment_tag": "QTY",
        "quantity_qualifier-6063": "220",
        "quantity_value-6060": "0,044",
        "quantity_unit-6411": null
    },
    {
        "segment_tag": "DTM",
        "function_code-2005": "163",
        "value-2380": "202412251100+00",
        "format_code-2379": "303"
    },
    {
        "segment_tag": "DTM",
        "function_code-2005": "164",
        "value-2380": "202412251115+00",
        "format_code-2379": "303"
    },
    {
        "segment_tag": "QTY",
        "quantity_qualifier-6063": "220",
        "quantity_value-6060": "0,043",
        "quantity_unit-6411": null
    },
    {
        "segment_tag": "DTM",
        "function_code-2005": "163",
        "value-2380": "202412251115+00",
        "format_code-2379": "303"
    },
    {
        "segment_tag": "DTM",
        "function_code-2005": "164",
        "value-2380": "202412251130+00",
        "format_code-2379": "303"
    },
    {
        "segment_tag": "QTY",
        "quantity_qualifier-6063": "220",
        "quantity_value-6060": "0,041",
        "quantity_unit-6411": null
    },
    {
        "segment_tag": "DTM",
        "function_code-2005": "163",
        "value-2380": "202412251130+00",
        "format_code-2379": "303"
    },
    {
        "segment_tag": "DTM",
        "function_code-2005": "164",
        "value-2380": "202412251145+00",
        "format_code-2379": "303"
    },
    {
        "segment_tag": "QTY",
        "quantity_qualifier-6063": "220",
        "quantity_value-6060": "0,051",
        "quantity_unit-6411": null
    },
    {
        "segment_tag": "DTM",
        "function_code-2005": "163",
        "value-2380": "202412251145+00",
        "format_code-2379": "303"
    },
    {
        "segment_tag": "DTM",
        "function_code-2005": "164",
        "value-2380": "202412251200+00",
        "format_code-2379": "303"
    },
    {
        "segment_tag": "QTY",
        "quantity_qualifier-6063": "220",
        "quantity_value-6060": "0,058",
        "quantity_unit-6411": null
    },
    {
        "segment_tag": "DTM",
        "function_code-2005": "163",
        "value-2380": "202412251200+00",
        "format_code-2379": "303"
    },
    {
        "segment_tag": "DTM",
        "function_code-2005": "164",
        "value-2380": "202412251215+00",
        "format_code-2379": "303"
    },
    {
        "segment_tag": "QTY",
        "quantity_qualifier-6063": "220",
        "quantity_value-6060": "0,069",
        "quantity_unit-6411": null
    },
    {
        "segment_tag": "DTM",
        "function_code-2005": "163",
        "value-2380": "202412251215+00",
        "format_code-2379": "303"
    },
    {
        "segment_tag": "DTM",
        "function_code-2005": "164",
        "value-2380": "202412251230+00",
        "format_code-2379": "303"
    },
    {
        "segment_tag": "QTY",
        "quantity_qualifier-6063": "220",
        "quantity_value-6060": "0,043",
        "quantity_unit-6411": null
    },
    {
        "segment_tag": "DTM",
        "function_code-2005": "163",
        "value-2380": "202412251230+00",
        "format_code-2379": "303"
    },
    {
        "segment_tag": "DTM",
        "function_code-2005": "164",
        "value-2380": "202412251245+00",
        "format_code-2379": "303"
    },
    {
        "segment_tag": "QTY",
        "quantity_qualifier-6063": "220",
        "quantity_value-6060": "0,045",
        "quantity_unit-6411": null
    },
    {
        "segment_tag": "DTM",
        "function_code-2005": "163",
        "value-2380": "202412251245+00",
        "format_code-2379": "303"
    },
    {
        "segment_tag": "DTM",
        "function_code-2005": "164",
        "value-2380": "202412251300+00",
        "format_code-2379": "303"
    },
    {
        "segment_tag": "QTY",
        "quantity_qualifier-6063": "220",
        "quantity_value-6060": "0,044",
        "quantity_unit-6411": null
    },
    {
        "segment_tag": "DTM",
        "function_code-2005": "163",
        "value-2380": "202412251300+00",
        "format_code-2379": "303"
    },
    {
        "segment_tag": "DTM",
        "function_code-2005": "164",
        "value-2380": "202412251315+00",
        "format_code-2379": "303"
    },
    {
        "segment_tag": "QTY",
        "quantity_qualifier-6063": "220",
        "quantity_value-6060": "0,042",
        "quantity_unit-6411": null
    },
    {
        "segment_tag": "DTM",
        "function_code-2005": "163",
        "value-2380": "202412251315+00",
        "format_code-2379": "303"
    },
    {
        "segment_tag": "DTM",
        "function_code-2005": "164",
        "value-2380": "202412251330+00",
        "format_code-2379": "303"
    },
    {
        "segment_tag": "QTY",
        "quantity_qualifier-6063": "220",
        "quantity_value-6060": "0,109",
        "quantity_unit-6411": null
    },
    {
        "segment_tag": "DTM",
        "function_code-2005": "163",
        "value-2380": "202412251330+00",
        "format_code-2379": "303"
    },
    {
        "segment_tag": "DTM",
        "function_code-2005": "164",
        "value-2380": "202412251345+00",
        "format_code-2379": "303"
    },
    {
        "segment_tag": "QTY",
        "quantity_qualifier-6063": "220",
        "quantity_value-6060": "0,082",
        "quantity_unit-6411": null
    },
    {
        "segment_tag": "DTM",
        "function_code-2005": "163",
        "value-2380": "202412251345+00",
        "format_code-2379": "303"
    },
    {
        "segment_tag": "DTM",
        "function_code-2005": "164",
        "value-2380": "202412251400+00",
        "format_code-2379": "303"
    },
    {
        "segment_tag": "QTY",
        "quantity_qualifier-6063": "220",
        "quantity_value-6060": "0,072",
        "quantity_unit-6411": null
    },
    {
        "segment_tag": "DTM",
        "function_code-2005": "163",
        "value-2380": "202412251400+00",
        "format_code-2379": "303"
    },
    {
        "segment_tag": "DTM",
        "function_code-2005": "164",
        "value-2380": "202412251415+00",
        "format_code-2379": "303"
    },
    {
        "segment_tag": "QTY",
        "quantity_qualifier-6063": "220",
        "quantity_value-6060": "0,082",
        "quantity_unit-6411": null
    },
    {
        "segment_tag": "DTM",
        "function_code-2005": "163",
        "value-2380": "202412251415+00",
        "format_code-2379": "303"
    },
    {
        "segment_tag": "DTM",
        "function_code-2005": "164",
        "value-2380": "202412251430+00",
        "format_code-2379": "303"
    },
    {
        "segment_tag": "QTY",
        "quantity_qualifier-6063": "220",
        "quantity_value-6060": "0,065",
        "quantity_unit-6411": null
    },
    {
        "segment_tag": "DTM",
        "function_code-2005": "163",
        "value-2380": "202412251430+00",
        "format_code-2379": "303"
    },
    {
        "segment_tag": "DTM",
        "function_code-2005": "164",
        "value-2380": "202412251445+00",
        "format_code-2379": "303"
    },
    {
        "segment_tag": "QTY",
        "quantity_qualifier-6063": "220",
        "quantity_value-6060": "0,06",
        "quantity_unit-6411": null
    },
    {
        "segment_tag": "DTM",
        "function_code-2005": "163",
        "value-2380": "202412251445+00",
        "format_code-2379": "303"
    },
    {
        "segment_tag": "DTM",
        "function_code-2005": "164",
        "value-2380": "202412251500+00",
        "format_code-2379": "303"
    },
    {
        "segment_tag": "QTY",
        "quantity_qualifier-6063": "220",
        "quantity_value-6060": "0,072",
        "quantity_unit-6411": null
    },
    {
        "segment_tag": "DTM",
        "function_code-2005": "163",
        "value-2380": "202412251500+00",
        "format_code-2379": "303"
    },
    {
        "segment_tag": "DTM",
        "function_code-2005": "164",
        "value-2380": "202412251515+00",
        "format_code-2379": "303"
    },
    {
        "segment_tag": "QTY",
        "quantity_qualifier-6063": "220",
        "quantity_value-6060": "0,062",
        "quantity_unit-6411": null
    },
    {
        "segment_tag": "DTM",
        "function_code-2005": "163",
        "value-2380": "202412251515+00",
        "format_code-2379": "303"
    },
    {
        "segment_tag": "DTM",
        "function_code-2005": "164",
        "value-2380": "202412251530+00",
        "format_code-2379": "303"
    },
    {
        "segment_tag": "QTY",
        "quantity_qualifier-6063": "220",
        "quantity_value-6060": "0,063",
        "quantity_unit-6411": null
    },
    {
        "segment_tag": "DTM",
        "function_code-2005": "163",
        "value-2380": "202412251530+00",
        "format_code-2379": "303"
    },
    {
        "segment_tag": "DTM",
        "function_code-2005": "164",
        "value-2380": "202412251545+00",
        "format_code-2379": "303"
    },
    {
        "segment_tag": "QTY",
        "quantity_qualifier-6063": "220",
        "quantity_value-6060": "0,046",
        "quantity_unit-6411": null
    },
    {
        "segment_tag": "DTM",
        "function_code-2005": "163",
        "value-2380": "202412251545+00",
        "format_code-2379": "303"
    },
    {
        "segment_tag": "DTM",
        "function_code-2005": "164",
        "value-2380": "202412251600+00",
        "format_code-2379": "303"
    },
    {
        "segment_tag": "QTY",
        "quantity_qualifier-6063": "67",
        "quantity_value-6060": "0,053",
        "quantity_unit-6411": null
    },
    {
        "segment_tag": "DTM",
        "function_code-2005": "163",
        "value-2380": "202412251600+00",
        "format_code-2379": "303"
    },
    {
        "segment_tag": "DTM",
        "function_code-2005": "164",
        "value-2380": "202412251615+00",
        "format_code-2379": "303"
    },
    {
        "segment_tag": "STS",
        "status_category_code-9015": "Z32",
        "status_reason_code-9013": "ZJ2"
    },
    {
        "segment_tag": "STS",
        "status_category_code-9015": "Z34",
        "status_reason_code-9013": "ZB0"
    },
    {
        "segment_tag": "STS",
        "status_category_code-9015": "Z40",
        "status_reason_code-9013": "ZB0"
    },
    {
        "segment_tag": "QTY",
        "quantity_qualifier-6063": "67",
        "quantity_value-6060": "0,053",
        "quantity_unit-6411": null
    },
    {
        "segment_tag": "DTM",
        "function_code-2005": "163",
        "value-2380": "202412251615+00",
        "format_code-2379": "303"
    },
    {
        "segment_tag": "DTM",
        "function_code-2005": "164",
        "value-2380": "202412251630+00",
        "format_code-2379": "303"
    },
    {
        "segment_tag": "STS",
        "status_category_code-9015": "Z32",
        "status_reason_code-9013": "ZJ2"
    },
    {
        "segment_tag": "STS",
        "status_category_code-9015": "Z34",
        "status_reason_code-9013": "ZB0"
    },
    {
        "segment_tag": "STS",
        "status_category_code-9015": "Z40",
        "status_reason_code-9013": "ZB0"
    },
    {
        "segment_tag": "QTY",
        "quantity_qualifier-6063": "220",
        "quantity_value-6060": "0,059",
        "quantity_unit-6411": null
    },
    {
        "segment_tag": "DTM",
        "function_code-2005": "163",
        "value-2380": "202412251630+00",
        "format_code-2379": "303"
    },
    {
        "segment_tag": "DTM",
        "function_code-2005": "164",
        "value-2380": "202412251645+00",
        "format_code-2379": "303"
    },
    {
        "segment_tag": "QTY",
        "quantity_qualifier-6063": "220",
        "quantity_value-6060": "0,044",
        "quantity_unit-6411": null
    },
    {
        "segment_tag": "DTM",
        "function_code-2005": "163",
        "value-2380": "202412251645+00",
        "format_code-2379": "303"
    },
    {
        "segment_tag": "DTM",
        "function_code-2005": "164",
        "value-2380": "202412251700+00",
        "format_code-2379": "303"
    },
    {
        "segment_tag": "QTY",
        "quantity_qualifier-6063": "220",
        "quantity_value-6060": "0,043",
        "quantity_unit-6411": null
    },
    {
        "segment_tag": "DTM",
        "function_code-2005": "163",
        "value-2380": "202412251700+00",
        "format_code-2379": "303"
    },
    {
        "segment_tag": "DTM",
        "function_code-2005": "164",
        "value-2380": "202412251715+00",
        "format_code-2379": "303"
    },
    {
        "segment_tag": "QTY",
        "quantity_qualifier-6063": "220",
        "quantity_value-6060": "0,044",
        "quantity_unit-6411": null
    },
    {
        "segment_tag": "DTM",
        "function_code-2005": "163",
        "value-2380": "202412251715+00",
        "format_code-2379": "303"
    },
    {
        "segment_tag": "DTM",
        "function_code-2005": "164",
        "value-2380": "202412251730+00",
        "format_code-2379": "303"
    },
    {
        "segment_tag": "QTY",
        "quantity_qualifier-6063": "220",
        "quantity_value-6060": "0,028",
        "quantity_unit-6411": null
    },
    {
        "segment_tag": "DTM",
        "function_code-2005": "163",
        "value-2380": "202412251730+00",
        "format_code-2379": "303"
    },
    {
        "segment_tag": "DTM",
        "function_code-2005": "164",
        "value-2380": "202412251745+00",
        "format_code-2379": "303"
    },
    {
        "segment_tag": "QTY",
        "quantity_qualifier-6063": "220",
        "quantity_value-6060": "0,049",
        "quantity_unit-6411": null
    },
    {
        "segment_tag": "DTM",
        "function_code-2005": "163",
        "value-2380": "202412251745+00",
        "format_code-2379": "303"
    },
    {
        "segment_tag": "DTM",
        "function_code-2005": "164",
        "value-2380": "202412251800+00",
        "format_code-2379": "303"
    },
    {
        "segment_tag": "QTY",
        "quantity_qualifier-6063": "220",
        "quantity_value-6060": "1,202",
        "quantity_unit-6411": null
    },
    {
        "segment_tag": "DTM",
        "function_code-2005": "163",
        "value-2380": "202412251800+00",
        "format_code-2379": "303"
    },
    {
        "segment_tag": "DTM",
        "function_code-2005": "164",
        "value-2380": "202412251815+00",
        "format_code-2379": "303"
    },
    {
        "segment_tag": "QTY",
        "quantity_qualifier-6063": "220",
        "quantity_value-6060": "1,758",
        "quantity_unit-6411": null
    },
    {
        "segment_tag": "DTM",
        "function_code-2005": "163",
        "value-2380": "202412251815+00",
        "format_code-2379": "303"
    },
    {
        "segment_tag": "DTM",
        "function_code-2005": "164",
        "value-2380": "202412251830+00",
        "format_code-2379": "303"
    },
    {
        "segment_tag": "QTY",
        "quantity_qualifier-6063": "220",
        "quantity_value-6060": "1,874",
        "quantity_unit-6411": null
    },
    {
        "segment_tag": "DTM",
        "function_code-2005": "163",
        "value-2380": "202412251830+00",
        "format_code-2379": "303"
    },
    {
        "segment_tag": "DTM",
        "function_code-2005": "164",
        "value-2380": "202412251845+00",
        "format_code-2379": "303"
    },
    {
        "segment_tag": "QTY",
        "quantity_qualifier-6063": "67",
        "quantity_value-6060": "1,298",
        "quantity_unit-6411": null
    },
    {
        "segment_tag": "DTM",
        "function_code-2005": "163",
        "value-2380": "202412251845+00",
        "format_code-2379": "303"
    },
    {
        "segment_tag": "DTM",
        "function_code-2005": "164",
        "value-2380": "202412251900+00",
        "format_code-2379": "303"
    },
    {
        "segment_tag": "STS",
        "status_category_code-9015": "Z32",
        "status_reason_code-9013": "ZJ2"
    },
    {
        "segment_tag": "STS",
        "status_category_code-9015": "Z34",
        "status_reason_code-9013": "ZB0"
    },
    {
        "segment_tag": "STS",
        "status_category_code-9015": "Z40",
        "status_reason_code-9013": "ZB0"
    },
    {
        "segment_tag": "QTY",
        "quantity_qualifier-6063": "67",
        "quantity_value-6060": "1,298",
        "quantity_unit-6411": null
    },
    {
        "segment_tag": "DTM",
        "function_code-2005": "163",
        "value-2380": "202412251900+00",
        "format_code-2379": "303"
    },
    {
        "segment_tag": "DTM",
        "function_code-2005": "164",
        "value-2380": "202412251915+00",
        "format_code-2379": "303"
    },
    {
        "segment_tag": "STS",
        "status_category_code-9015": "Z32",
        "status_reason_code-9013": "ZJ2"
    },
    {
        "segment_tag": "STS",
        "status_category_code-9015": "Z34",
        "status_reason_code-9013": "ZB0"
    },
    {
        "segment_tag": "STS",
        "status_category_code-9015": "Z40",
        "status_reason_code-9013": "ZB0"
    },
    {
        "segment_tag": "QTY",
        "quantity_qualifier-6063": "67",
        "quantity_value-6060": "1,298",
        "quantity_unit-6411": null
    },
    {
        "segment_tag": "DTM",
        "function_code-2005": "163",
        "value-2380": "202412251915+00",
        "format_code-2379": "303"
    },
    {
        "segment_tag": "DTM",
        "function_code-2005": "164",
        "value-2380": "202412251930+00",
        "format_code-2379": "303"
    },
    {
        "segment_tag": "STS",
        "status_category_code-9015": "Z32",
        "status_reason_code-9013": "ZJ2"
    },
    {
        "segment_tag": "STS",
        "status_category_code-9015": "Z34",
        "status_reason_code-9013": "ZB0"
    },
    {
        "segment_tag": "STS",
        "status_category_code-9015": "Z40",
        "status_reason_code-9013": "ZB0"
    },
    {
        "segment_tag": "QTY",
        "quantity_qualifier-6063": "220",
        "quantity_value-6060": "1,206",
        "quantity_unit-6411": null
    },
    {
        "segment_tag": "DTM",
        "function_code-2005": "163",
        "value-2380": "202412251930+00",
        "format_code-2379": "303"
    },
    {
        "segment_tag": "DTM",
        "function_code-2005": "164",
        "value-2380": "202412251945+00",
        "format_code-2379": "303"
    },
    {
        "segment_tag": "QTY",
        "quantity_qualifier-6063": "220",
        "quantity_value-6060": "1,323",
        "quantity_unit-6411": null
    },
    {
        "segment_tag": "DTM",
        "function_code-2005": "163",
        "value-2380": "202412251945+00",
        "format_code-2379": "303"
    },
    {
        "segment_tag": "DTM",
        "function_code-2005": "164",
        "value-2380": "202412252000+00",
        "format_code-2379": "303"
    },
    {
        "segment_tag": "QTY",
        "quantity_qualifier-6063": "220",
        "quantity_value-6060": "1,162",
        "quantity_unit-6411": null
    },
    {
        "segment_tag": "DTM",
        "function_code-2005": "163",
        "value-2380": "202412252000+00",
        "format_code-2379": "303"
    },
    {
        "segment_tag": "DTM",
        "function_code-2005": "164",
        "value-2380": "202412252015+00",
        "format_code-2379": "303"
    },
    {
        "segment_tag": "QTY",
        "quantity_qualifier-6063": "67",
        "quantity_value-6060": "1,344",
        "quantity_unit-6411": null
    },
    {
        "segment_tag": "DTM",
        "function_code-2005": "163",
        "value-2380": "202412252015+00",
        "format_code-2379": "303"
    },
    {
        "segment_tag": "DTM",
        "function_code-2005": "164",
        "value-2380": "202412252030+00",
        "format_code-2379": "303"
    },
    {
        "segment_tag": "STS",
        "status_category_code-9015": "Z32",
        "status_reason_code-9013": "ZJ2"
    },
    {
        "segment_tag": "STS",
        "status_category_code-9015": "Z34",
        "status_reason_code-9013": "ZB0"
    },
    {
        "segment_tag": "STS",
        "status_category_code-9015": "Z40",
        "status_reason_code-9013": "ZB0"
    },
    {
        "segment_tag": "QTY",
        "quantity_qualifier-6063": "67",
        "quantity_value-6060": "1,344",
        "quantity_unit-6411": null
    },
    {
        "segment_tag": "DTM",
        "function_code-2005": "163",
        "value-2380": "202412252030+00",
        "format_code-2379": "303"
    },
    {
        "segment_tag": "DTM",
        "function_code-2005": "164",
        "value-2380": "202412252045+00",
        "format_code-2379": "303"
    },
    {
        "segment_tag": "STS",
        "status_category_code-9015": "Z32",
        "status_reason_code-9013": "ZJ2"
    },
    {
        "segment_tag": "STS",
        "status_category_code-9015": "Z34",
        "status_reason_code-9013": "ZB0"
    },
    {
        "segment_tag": "STS",
        "status_category_code-9015": "Z40",
        "status_reason_code-9013": "ZB0"
    },
    {
        "segment_tag": "QTY",
        "quantity_qualifier-6063": "220",
        "quantity_value-6060": "2,165",
        "quantity_unit-6411": null
    },
    {
        "segment_tag": "DTM",
        "function_code-2005": "163",
        "value-2380": "202412252045+00",
        "format_code-2379": "303"
    },
    {
        "segment_tag": "DTM",
        "function_code-2005": "164",
        "value-2380": "202412252100+00",
        "format_code-2379": "303"
    },
    {
        "segment_tag": "QTY",
        "quantity_qualifier-6063": "220",
        "quantity_value-6060": "1,724",
        "quantity_unit-6411": null
    },
    {
        "segment_tag": "DTM",
        "function_code-2005": "163",
        "value-2380": "202412252100+00",
        "format_code-2379": "303"
    },
    {
        "segment_tag": "DTM",
        "function_code-2005": "164",
        "value-2380": "202412252115+00",
        "format_code-2379": "303"
    },
    {
        "segment_tag": "QTY",
        "quantity_qualifier-6063": "220",
        "quantity_value-6060": "1,262",
        "quantity_unit-6411": null
    },
    {
        "segment_tag": "DTM",
        "function_code-2005": "163",
        "value-2380": "202412252115+00",
        "format_code-2379": "303"
    },
    {
        "segment_tag": "DTM",
        "function_code-2005": "164",
        "value-2380": "202412252130+00",
        "format_code-2379": "303"
    },
    {
        "segment_tag": "QTY",
        "quantity_qualifier-6063": "220",
        "quantity_value-6060": "1,126",
        "quantity_unit-6411": null
    },
    {
        "segment_tag": "DTM",
        "function_code-2005": "163",
        "value-2380": "202412252130+00",
        "format_code-2379": "303"
    },
    {
        "segment_tag": "DTM",
        "function_code-2005": "164",
        "value-2380": "202412252145+00",
        "format_code-2379": "303"
    },
    {
        "segment_tag": "QTY",
        "quantity_qualifier-6063": "67",
        "quantity_value-6060": "1,139",
        "quantity_unit-6411": null
    },
    {
        "segment_tag": "DTM",
        "function_code-2005": "163",
        "value-2380": "202412252145+00",
        "format_code-2379": "303"
    },
    {
        "segment_tag": "DTM",
        "function_code-2005": "164",
        "value-2380": "202412252200+00",
        "format_code-2379": "303"
    },
    {
        "segment_tag": "STS",
        "status_category_code-9015": "Z32",
        "status_reason_code-9013": "ZJ2"
    },
    {
        "segment_tag": "STS",
        "status_category_code-9015": "Z34",
        "status_reason_code-9013": "ZB0"
    },
    {
        "segment_tag": "STS",
        "status_category_code-9015": "Z40",
        "status_reason_code-9013": "ZB0"
    },
    {
        "segment_tag": "QTY",
        "quantity_qualifier-6063": "67",
        "quantity_value-6060": "1,139",
        "quantity_unit-6411": null
    },
    {
        "segment_tag": "DTM",
        "function_code-2005": "163",
        "value-2380": "202412252200+00",
        "format_code-2379": "303"
    },
    {
        "segment_tag": "DTM",
        "function_code-2005": "164",
        "value-2380": "202412252215+00",
        "format_code-2379": "303"
    },
    {
        "segment_tag": "STS",
        "status_category_code-9015": "Z32",
        "status_reason_code-9013": "ZJ2"
    },
    {
        "segment_tag": "STS",
        "status_category_code-9015": "Z34",
        "status_reason_code-9013": "ZB0"
    },
    {
        "segment_tag": "STS",
        "status_category_code-9015": "Z40",
        "status_reason_code-9013": "ZB0"
    },
    {
        "segment_tag": "QTY",
        "quantity_qualifier-6063": "220",
        "quantity_value-6060": "1,022",
        "quantity_unit-6411": null
    },
    {
        "segment_tag": "DTM",
        "function_code-2005": "163",
        "value-2380": "202412252215+00",
        "format_code-2379": "303"
    },
    {
        "segment_tag": "DTM",
        "function_code-2005": "164",
        "value-2380": "202412252230+00",
        "format_code-2379": "303"
    },
    {
        "segment_tag": "QTY",
        "quantity_qualifier-6063": "220",
        "quantity_value-6060": "1,394",
        "quantity_unit-6411": null
    },
    {
        "segment_tag": "DTM",
        "function_code-2005": "163",
        "value-2380": "202412252230+00",
        "format_code-2379": "303"
    },
    {
        "segment_tag": "DTM",
        "function_code-2005": "164",
        "value-2380": "202412252245+00",
        "format_code-2379": "303"
    },
    {
        "segment_tag": "QTY",
        "quantity_qualifier-6063": "220",
        "quantity_value-6060": "1,721",
        "quantity_unit-6411": null
    },
    {
        "segment_tag": "DTM",
        "function_code-2005": "163",
        "value-2380": "202412252245+00",
        "format_code-2379": "303"
    },
    {
        "segment_tag": "DTM",
        "function_code-2005": "164",
        "value-2380": "202412252300+00",
        "format_code-2379": "303"
    },
    {
        "segment_tag": "UNT",
        "number_of_segments-0074": "335",
        "message_reference_number-0062": "1"
    },
    {
        "segment_tag": "UNZ",
        "interchange_control_count-0036": "1",
        "interchange_control_reference-0020": "CS0000000GA0FI"
    }
]