[
    {
        "segment_tag": "UNB",
        "syntax": {
            "identifier-0001": "UNOC",
            "version-0002": "3"
        },
        "sender": {
            "id-0004": "9905048000007",
            "qualifier-0007": "500"
        },
        "receiver": {
            "id-0010": "9985046000001",
            "qualifier-0007": "500"
        },
        "datetime": {
            "date-0017": "250109",
            "time-0019": "1429"
        },
        "reference-0020": "CS0000000GAZ6Y",
        "application_ref-0026": "TL"
    },
    {
        "segment_tag": "UNH",
        "message_reference-0062": "1",
        "message_type": {
            "message_type_id-0065": "MSCONS",
            "message_version-0052": "D",
            "message_release-0054": "04B",
            "controlling_agency-0051": "UN",
            "association_code-0057": "2.4c",
            "common_access_ref-0068": null
        },
        "transmission": {
            "sequence_number-0070": null,
            "sequence_status-0073": null
        }
    },
    {
        "segment_tag": "BGM",
        "document_code-1001": "Z48",
        "document_name-1001": "Lastgang Marktlokation, Tranche",
        "document_number-1004": "CS0000000GAZ6Y-1",
        "message_function_code-1225": "9"
    },
    {
        "segment_tag": "DTM",
        "function_code-2005": "137",
        "value-2380": "202501091429+00",
        "format_code-2379": "303"
    },
    {
        "segment_tag": "RFF",
        "qualifier-1153": "Z13",
        "identifier-1154": "13025"
    },
    {
        "segment_tag": "NAD",
        "party_qualifier-3035": "MS",
        "party_id-3039": "9905048000007",
        "code_list-1131": "",
        "resp_agency-3055": "293"
    },
    {
        "segment_tag": "NAD",
        "party_qualifier-3035": "MR",
        "party_id-3039": "9985046000001",
        "code_list-1131": "",
        "resp_agency-3055": "293"
    },
    {
        "segment_tag": "UNS",
        "section_id-0081": "D"
    },
    {
        "segment_tag": "NAD",
        "party_qualifier-3035": "DP",
        "party_id-3039": null,
        "code_list-1131": null,
        "resp_agency-3055": null
    },
    {
        "segment_tag": "LOC",
        "location_qualifier-3227": "172",
        "location_code-3225": "50120962218",
        "first_related_code-3223": null
    },
    {
        "segment_tag": "DTM",
        "function_code-2005": "163",
        "value-2380": "202412302300+00",
        "format_code-2379": "303"
    },
    {
        "segment_tag": "DTM",
        "function_code-2005": "164",
        "value-2380": "202412312300+00",
        "format_code-2379": "303"
    },
    {
        "segment_tag": "LIN",
        "line_item_number-1082": "1"
    },
    {
        "segment_tag": "PIA",
        "qualifier-4347": "5",
        "product_number-7140": "1-1:1.29.0",
        "product_type-7143": "SRW"
    },
    {
        "segment_tag": "QTY",
        "quantity_qualifier-6063": "220",
        "quantity_value-6060": "1,903",
        "quantity_unit-6411": null
    },
    {
        "segment_tag": "DTM",
        "function_code-2005": "163",
        "value-2380": "202412302300+00",
        "format_code-2379": "303"
    },
    {
        "segment_tag": "DTM",
        "function_code-2005": "164",
        "value-2380": "202412302315+00",
        "format_code-2379": "303"
    },
    {
        "segment_tag": "STS",
        "status_category_code-9015": "Z34",
        "status_reason_code-9013": "ZA4"
    },
    {
        "segment_tag": "QTY",
        "quantity_qualifier-6063": "220",
        "quantity_value-6060": "1,7",
        "quantity_unit-6411": null
    },
    {
        "segment_tag": "DTM",
        "function_code-2005": "163",
        "value-2380": "202412302315+00",
        "format_code-2379": "303"
    },
    {
        "segment_tag": "DTM",
        "function_code-2005": "164",
        "value-2380": "202412302330+00",
        "format_code-2379": "303"
    },
    {
        "segment_tag": "STS",
        "status_category_code-9015": "Z34",
        "status_reason_code-9013": "ZA4"
    },
    {
        "segment_tag": "QTY",
        "quantity_qualifier-6063": "220",
        "quantity_value-6060": "1,319",
        "quantity_unit-6411": null
    },
    {
        "segment_tag": "DTM",
        "function_code-2005": "163",
        "value-2380": "202412302330+00",
        "format_code-2379": "303"
    },
    {
        "segment_tag": "DTM",
        "function_code-2005": "164",
        "value-2380": "202412302345+00",
        "format_code-2379": "303"
    },
    {
        "segment_tag": "STS",
        "status_category_code-9015": "Z34",
        "status_reason_code-9013": "ZA4"
    },
    {
        "segment_tag": "QTY",
        "quantity_qualifier-6063": "67",
        "quantity_value-6060": "2,302",
        "quantity_unit-6411": null
    },
    {
        "segment_tag": "DTM",
        "function_code-2005": "163",
        "value-2380": "202412302345+00",
        "format_code-2379": "303"
    },
    {
        "segment_tag": "DTM",
        "function_code-2005": "164",
        "value-2380": "202412310000+00",
        "format_code-2379": "303"
    },
    {
        "segment_tag": "STS",
        "status_category_code-9015": "Z32",
        "status_reason_code-9013": "ZJ2"
    },
    {
        "segment_tag": "STS",
        "status_category_code-9015": "Z34",
        "status_reason_code-9013": "ZB0"
    },
    {
        "segment_tag": "STS",
        "status_category_code-9015": "Z40",
        "status_reason_code-9013": "ZB0"
    },
    {
        "segment_tag": "QTY",
        "quantity_qualifier-6063": "67",
        "quantity_value-6060": "2,302",
        "quantity_unit-6411": null
    },
    {
        "segment_tag": "DTM",
        "function_code-2005": "163",
        "value-2380": "202412310000+00",
        "format_code-2379": "303"
    },
    {
        "segment_tag": "DTM",
        "function_code-2005": "164",
        "value-2380": "202412310015+00",
        "format_code-2379": "303"
    },
    {
        "segment_tag": "STS",
        "status_category_code-9015": "Z32",
        "status_reason_code-9013": "ZJ2"
    },
    {
        "segment_tag": "STS",
        "status_category_code-9015": "Z34",
        "status_reason_code-9013": "ZB0"
    },
    {
        "segment_tag": "STS",
        "status_category_code-9015": "Z40",
        "status_reason_code-9013": "ZB0"
    },
    {
        "segment_tag": "QTY",
        "quantity_qualifier-6063": "220",
        "quantity_value-6060": "2,91",
        "quantity_unit-6411": null
    },
    {
        "segment_tag": "DTM",
        "function_code-2005": "163",
        "value-2380": "202412310015+00",
        "format_code-2379": "303"
    },
    {
        "segment_tag": "DTM",
        "function_code-2005": "164",
        "value-2380": "202412310030+00",
        "format_code-2379": "303"
    },
    {
        "segment_tag": "STS",
        "status_category_code-9015": "Z34",
        "status_reason_code-9013": "ZA4"
    },
    {
        "segment_tag": "QTY",
        "quantity_qualifier-6063": "220",
        "quantity_value-6060": "3,889",
        "quantity_unit-6411": null
    },
    {
        "segment_tag": "DTM",
        "function_code-2005": "163",
        "value-2380": "202412310030+00",
        "format_code-2379": "303"
    },
    {
        "segment_tag": "DTM",
        "function_code-2005": "164",
        "value-2380": "202412310045+00",
        "format_code-2379": "303"
    },
    {
        "segment_tag": "STS",
        "status_category_code-9015": "Z34",
        "status_reason_code-9013": "ZA4"
    },
    {
        "segment_tag": "QTY",
        "quantity_qualifier-6063": "220",
        "quantity_value-6060": "3,116",
        "quantity_unit-6411": null
    },
    {
        "segment_tag": "DTM",
        "function_code-2005": "163",
        "value-2380": "202412310045+00",
        "format_code-2379": "303"
    },
    {
        "segment_tag": "DTM",
        "function_code-2005": "164",
        "value-2380": "202412310100+00",
        "format_code-2379": "303"
    },
    {
        "segment_tag": "STS",
        "status_category_code-9015": "Z34",
        "status_reason_code-9013": "ZA4"
    },
    {
        "segment_tag": "QTY",
        "quantity_qualifier-6063": "220",
        "quantity_value-6060": "0,071",
        "quantity_unit-6411": null
    },
    {
        "segment_tag": "DTM",
        "function_code-2005": "163",
        "value-2380": "202412310100+00",
        "format_code-2379": "303"
    },
    {
        "segment_tag": "DTM",
        "function_code-2005": "164",
        "value-2380": "202412310115+00",
        "format_code-2379": "303"
    },
    {
        "segment_tag": "STS",
        "status_category_code-9015": "Z34",
        "status_reason_code-9013": "ZA4"
    },
    {
        "segment_tag": "QTY",
        "quantity_qualifier-6063": "220",
        "quantity_value-6060": "1,673",
        "quantity_unit-6411": null
    },
    {
        "segment_tag": "DTM",
        "function_code-2005": "163",
        "value-2380": "202412310115+00",
        "format_code-2379": "303"
    },
    {
        "segment_tag": "DTM",
        "function_code-2005": "164",
        "value-2380": "202412310130+00",
        "format_code-2379": "303"
    },
    {
        "segment_tag": "STS",
        "status_category_code-9015": "Z34",
        "status_reason_code-9013": "ZA4"
    },
    {
        "segment_tag": "QTY",
        "quantity_qualifier-6063": "220",
        "quantity_value-6060": "1,442",
        "quantity_unit-6411": null
    },
    {
        "segment_tag": "DTM",
        "function_code-2005": "163",
        "value-2380": "202412310130+00",
        "format_code-2379": "303"
    },
    {
        "segment_tag": "DTM",
        "function_code-2005": "164",
        "value-2380": "202412310145+00",
        "format_code-2379": "303"
    },
    {
        "segment_tag": "STS",
        "status_category_code-9015": "Z34",
        "status_reason_code-9013": "ZA4"
    },
    {
        "segment_tag": "QTY",
        "quantity_qualifier-6063": "220",
        "quantity_value-6060": "1,538",
        "quantity_unit-6411": null
    },
    {
        "segment_tag": "DTM",
        "function_code-2005": "163",
        "value-2380": "202412310145+00",
        "format_code-2379": "303"
    },
    {
        "segment_tag": "DTM",
        "function_code-2005": "164",
        "value-2380": "202412310200+00",
        "format_code-2379": "303"
    },
    {
        "segment_tag": "STS",
        "status_category_code-9015": "Z34",
        "status_reason_code-9013": "ZA4"
    },
    {
        "segment_tag": "QTY",
        "quantity_qualifier-6063": "220",
        "quantity_value-6060": "1,712",
        "quantity_unit-6411": null
    },
    {
        "segment_tag": "DTM",
        "function_code-2005": "163",
        "value-2380": "202412310200+00",
        "format_code-2379": "303"
    },
    {
        "segment_tag": "DTM",
        "function_code-2005": "164",
        "value-2380": "202412310215+00",
        "format_code-2379": "303"
    },
    {
        "segment_tag": "STS",
        "status_category_code-9015": "Z34",
        "status_reason_code-9013": "ZA4"
    },
    {
        "segment_tag": "QTY",
        "quantity_qualifier-6063": "220",
        "quantity_value-6060": "2,374",
        "quantity_unit-6411": null
    },
    {
        "segment_tag": "DTM",
        "function_code-2005": "163",
        "value-2380": "202412310215+00",
        "format_code-2379": "303"
    },
    {
        "segment_tag": "DTM",
        "function_code-2005": "164",
        "value-2380": "202412310230+00",
        "format_code-2379": "303"
    },
    {
        "segment_tag": "STS",
        "status_category_code-9015": "Z34",
        "status_reason_code-9013": "ZA4"
    },
    {
        "segment_tag": "QTY",
        "quantity_qualifier-6063": "220",
        "quantity_value-6060": "2,195",
        "quantity_unit-6411": null
    },
    {
        "segment_tag": "DTM",
        "function_code-2005": "163",
        "value-2380": "202412310230+00",
        "format_code-2379": "303"
    },
    {
        "segment_tag": "DTM",
        "function_code-2005": "164",
        "value-2380": "202412310245+00",
        "format_code-2379": "303"
    },
    {
        "segment_tag": "STS",
        "status_category_code-9015": "Z34",
        "status_reason_code-9013": "ZA4"
    },
    {
        "segment_tag": "QTY",
        "quantity_qualifier-6063": "220",
        "quantity_value-6060": "3,547",
        "quantity_unit-6411": null
    },
    {
        "segment_tag": "DTM",
        "function_code-2005": "163",
        "value-2380": "202412310245+00",
        "format_code-2379": "303"
    },
    {
        "segment_tag": "DTM",
        "function_code-2005": "164",
        "value-2380": "202412310300+00",
        "format_code-2379": "303"
    },
    {
        "segment_tag": "STS",
        "status_category_code-9015": "Z34",
        "status_reason_code-9013": "ZA4"
    },
    {
        "segment_tag": "QTY",
        "quantity_qualifier-6063": "220",
        "quantity_value-6060": "3,5",
        "quantity_unit-6411": null
    },
    {
        "segment_tag": "DTM",
        "function_code-2005": "163",
        "value-2380": "202412310300+00",
        "format_code-2379": "303"
    },
    {
        "segment_tag": "DTM",
        "function_code-2005": "164",
        "value-2380": "202412310315+00",
        "format_code-2379": "303"
    },
    {
        "segment_tag": "STS",
        "status_category_code-9015": "Z34",
        "status_reason_code-9013": "ZA4"
    },
    {
        "segment_tag": "QTY",
        "quantity_qualifier-6063": "220",
        "quantity_value-6060": "4,056",
        "quantity_unit-6411": null
    },
    {
        "segment_tag": "DTM",
        "function_code-2005": "163",
        "value-2380": "202412310315+00",
        "format_code-2379": "303"
    },
    {
        "segment_tag": "DTM",
        "function_code-2005": "164",
        "value-2380": "202412310330+00",
        "format_code-2379": "303"
    },
    {
        "segment_tag": "STS",
        "status_category_code-9015": "Z34",
        "status_reason_code-9013": "ZA4"
    },
    {
        "segment_tag": "QTY",
        "quantity_qualifier-6063": "220",
        "quantity_value-6060": "3,707",
        "quantity_unit-6411": null
    },
    {
        "segment_tag": "DTM",
        "function_code-2005": "163",
        "value-2380": "202412310330+00",
        "format_code-2379": "303"
    },
    {
        "segment_tag": "DTM",
        "function_code-2005": "164",
        "value-2380": "202412310345+00",
        "format_code-2379": "303"
    },
    {
        "segment_tag": "STS",
        "status_category_code-9015": "Z34",
        "status_reason_code-9013": "ZA4"
    },
    {
        "segment_tag": "QTY",
        "quantity_qualifier-6063": "220",
        "quantity_value-6060": "2,177",
        "quantity_unit-6411": null
    },
    {
        "segment_tag": "DTM",
        "function_code-2005": "163",
        "value-2380": "202412310345+00",
        "format_code-2379": "303"
    },
    {
        "segment_tag": "DTM",
        "function_code-2005": "164",
        "value-2380": "202412310400+00",
        "format_code-2379": "303"
    },
    {
        "segment_tag": "STS",
        "status_category_code-9015": "Z34",
        "status_reason_code-9013": "ZA4"
    },
    {
        "segment_tag": "QTY",
        "quantity_qualifier-6063": "220",
        "quantity_value-6060": "1,388",
        "quantity_unit-6411": null
    },
    {
        "segment_tag": "DTM",
        "function_code-2005": "163",
        "value-2380": "202412310400+00",
        "format_code-2379": "303"
    },
    {
        "segment_tag": "DTM",
        "function_code-2005": "164",
        "value-2380": "202412310415+00",
        "format_code-2379": "303"
    },
    {
        "segment_tag": "STS",
        "status_category_code-9015": "Z34",
        "status_reason_code-9013": "ZA4"
    },
    {
        "segment_tag": "QTY",
        "quantity_qualifier-6063": "220",
        "quantity_value-6060": "1,465",
        "quantity_unit-6411": null
    },
    {
        "segment_tag": "DTM",
        "function_code-2005": "163",
        "value-2380": "202412310415+00",
        "format_code-2379": "303"
    },
    {
        "segment_tag": "DTM",
        "function_code-2005": "164",
        "value-2380": "202412310430+00",
        "format_code-2379": "303"
    },
    {
        "segment_tag": "STS",
        "status_category_code-9015": "Z34",
        "status_reason_code-9013": "ZA4"
    },
    {
        "segment_tag": "QTY",
        "quantity_qualifier-6063": "220",
        "quantity_value-6060": "1,697",
        "quantity_unit-6411": null
    },
    {
        "segment_tag": "DTM",
        "function_code-2005": "163",
        "value-2380": "202412310430+00",
        "format_code-2379": "303"
    },
    {
        "segment_tag": "DTM",
        "function_code-2005": "164",
        "value-2380": "202412310445+00",
        "format_code-2379": "303"
    },
    {
        "segment_tag": "STS",
        "status_category_code-9015": "Z34",
        "status_reason_code-9013": "ZA4"
    },
    {
        "segment_tag": "QTY",
        "quantity_qualifier-6063": "220",
        "quantity_value-6060": "1,523",
        "quantity_unit-6411": null
    },
    {
        "segment_tag": "DTM",
        "function_code-2005": "163",
        "value-2380": "202412310445+00",
        "format_code-2379": "303"
    },
    {
        "segment_tag": "DTM",
        "function_code-2005": "164",
        "value-2380": "202412310500+00",
        "format_code-2379": "303"
    },
    {
        "segment_tag": "STS",
        "status_category_code-9015": "Z34",
        "status_reason_code-9013": "ZA4"
    },
    {
        "segment_tag": "QTY",
        "quantity_qualifier-6063": "220",
        "quantity_value-6060": "1,854",
        "quantity_unit-6411": null
    },
    {
        "segment_tag": "DTM",
        "function_code-2005": "163",
        "value-2380": "202412310500+00",
        "format_code-2379": "303"
    },
    {
        "segment_tag": "DTM",
        "function_code-2005": "164",
        "value-2380": "202412310515+00",
        "format_code-2379": "303"
    },
    {
        "segment_tag": "STS",
        "status_category_code-9015": "Z34",
        "status_reason_code-9013": "ZA4"
    },
    {
        "segment_tag": "QTY",
        "quantity_qualifier-6063": "220",
        "quantity_value-6060": "2,043",
        "quantity_unit-6411": null
    },
    {
        "segment_tag": "DTM",
        "function_code-2005": "163",
        "value-2380": "202412310515+00",
        "format_code-2379": "303"
    },
    {
        "segment_tag": "DTM",
        "function_code-2005": "164",
        "value-2380": "202412310530+00",
        "format_code-2379": "303"
    },
    {
        "segment_tag": "STS",
        "status_category_code-9015": "Z34",
        "status_reason_code-9013": "ZA4"
    },
    {
        "segment_tag": "QTY",
        "quantity_qualifier-6063": "220",
        "quantity_value-6060": "2,901",
        "quantity_unit-6411": null
    },
    {
        "segment_tag": "DTM",
        "function_code-2005": "163",
        "value-2380": "202412310530+00",
        "format_code-2379": "303"
    },
    {
        "segment_tag": "DTM",
        "function_code-2005": "164",
        "value-2380": "202412310545+00",
        "format_code-2379": "303"
    },
    {
        "segment_tag": "STS",
        "status_category_code-9015": "Z34",
        "status_reason_code-9013": "ZA4"
    },
    {
        "segment_tag": "QTY",
        "quantity_qualifier-6063": "220",
        "quantity_value-6060": "4,067",
        "quantity_unit-6411": null
    },
    {
        "segment_tag": "DTM",
        "function_code-2005": "163",
        "value-2380": "202412310545+00",
        "format_code-2379": "303"
    },
    {
        "segment_tag": "DTM",
        "function_code-2005": "164",
        "value-2380": "202412310600+00",
        "format_code-2379": "303"
    },
    {
        "segment_tag": "STS",
        "status_category_code-9015": "Z34",
        "status_reason_code-9013": "ZA4"
    },
    {
        "segment_tag": "QTY",
        "quantity_qualifier-6063": "220",
        "quantity_value-6060": "3,567",
        "quantity_unit-6411": null
    },
    {
        "segment_tag": "DTM",
        "function_code-2005": "163",
        "value-2380": "202412310600+00",
        "format_code-2379": "303"
    },
    {
        "segment_tag": "DTM",
        "function_code-2005": "164",
        "value-2380": "202412310615+00",
        "format_code-2379": "303"
    },
    {
        "segment_tag": "STS",
        "status_category_code-9015": "Z34",
        "status_reason_code-9013": "ZA4"
    },
    {
        "segment_tag": "QTY",
        "quantity_qualifier-6063": "220",
        "quantity_value-6060": "2,48",
        "quantity_unit-6411": null
    },
    {
        "segment_tag": "DTM",
        "function_code-2005": "163",
        "value-2380": "202412310615+00",
        "format_code-2379": "303"
    },
    {
        "segment_tag": "DTM",
        "function_code-2005": "164",
        "value-2380": "202412310630+00",
        "format_code-2379": "303"
    },
    {
        "segment_tag": "STS",
        "status_category_code-9015": "Z34",
        "status_reason_code-9013": "ZA4"
    },
    {
        "segment_tag": "QTY",
        "quantity_qualifier-6063": "220",
        "quantity_value-6060": "4,253",
        "quantity_unit-6411": null
    },
    {
        "segment_tag": "DTM",
        "function_code-2005": "163",
        "value-2380": "202412310630+00",
        "format_code-2379": "303"
    },
    {
        "segment_tag": "DTM",
        "function_code-2005": "164",
        "value-2380": "202412310645+00",
        "format_code-2379": "303"
    },
    {
        "segment_tag": "STS",
        "status_category_code-9015": "Z34",
        "status_reason_code-9013": "ZA4"
    },
    {
        "segment_tag": "QTY",
        "quantity_qualifier-6063": "220",
        "quantity_value-6060": "4,131",
        "quantity_unit-6411": null
    },
    {
        "segment_tag": "DTM",
        "function_code-2005": "163",
        "value-2380": "202412310645+00",
        "format_code-2379": "303"
    },
    {
        "segment_tag": "DTM",
        "function_code-2005": "164",
        "value-2380": "202412310700+00",
        "format_code-2379": "303"
    },
    {
        "segment_tag": "STS",
        "status_category_code-9015": "Z34",
        "status_reason_code-9013": "ZA4"
    },
    {
        "segment_tag": "QTY",
        "quantity_qualifier-6063": "220",
        "quantity_value-6060": "2,429",
        "quantity_unit-6411": null
    },
    {
        "segment_tag": "DTM",
        "function_code-2005": "163",
        "value-2380": "202412310700+00",
        "format_code-2379": "303"
    },
    {
        "segment_tag": "DTM",
        "function_code-2005": "164",
        "value-2380": "202412310715+00",
        "format_code-2379": "303"
    },
    {
        "segment_tag": "STS",
        "status_category_code-9015": "Z34",
        "status_reason_code-9013": "ZA4"
    },
    {
        "segment_tag": "QTY",
        "quantity_qualifier-6063": "220",
        "quantity_value-6060": "3,989",
        "quantity_unit-6411": null
    },
    {
        "segment_tag": "DTM",
        "function_code-2005": "163",
        "value-2380": "202412310715+00",
        "format_code-2379": "303"
    },
    {
        "segment_tag": "DTM",
        "function_code-2005": "164",
        "value-2380": "202412310730+00",
        "format_code-2379": "303"
    },
    {
        "segment_tag": "STS",
        "status_category_code-9015": "Z34",
        "status_reason_code-9013": "ZA4"
    },
    {
        "segment_tag": "QTY",
        "quantity_qualifier-6063": "220",
        "quantity_value-6060": "4,098",
        "quantity_unit-6411": null
    },
    {
        "segment_tag": "DTM",
        "function_code-2005": "163",
        "value-2380": "202412310730+00",
        "format_code-2379": "303"
    },
    {
        "segment_tag": "DTM",
        "function_code-2005": "164",
        "value-2380": "202412310745+00",
        "format_code-2379": "303"
    },
    {
        "segment_tag": "STS",
        "status_category_code-9015": "Z34",
        "status_reason_code-9013": "ZA4"
    },
    {
        "segment_tag": "QTY",
        "quantity_qualifier-6063": "220",
        "quantity_value-6060": "2,912",
        "quantity_unit-6411": null
    },
    {
        "segment_tag": "DTM",
        "function_code-2005": "163",
        "value-2380": "202412310745+00",
        "format_code-2379": "303"
    },
    {
        "segment_tag": "DTM",
        "function_code-2005": "164",
        "value-2380": "202412310800+00",
        "format_code-2379": "303"
    },
    {
        "segment_tag": "STS",
        "status_category_code-9015": "Z34",
        "status_reason_code-9013": "ZA4"
    },
    {
        "segment_tag": "QTY",
        "quantity_qualifier-6063": "220",
        "quantity_value-6060": "1,604",
        "quantity_unit-6411": null
    },
    {
        "segment_tag": "DTM",
        "function_code-2005": "163",
        "value-2380": "202412310800+00",
        "format_code-2379": "303"
    },
    {
        "segment_tag": "DTM",
        "function_code-2005": "164",
        "value-2380": "202412310815+00",
        "format_code-2379": "303"
    },
    {
        "segment_tag": "STS",
        "status_category_code-9015": "Z34",
        "status_reason_code-9013": "ZA4"
    },
    {
        "segment_tag": "QTY",
        "quantity_qualifier-6063": "220",
        "quantity_value-6060": "0,889",
        "quantity_unit-6411": null
    },
    {
        "segment_tag": "DTM",
        "function_code-2005": "163",
        "value-2380": "202412310815+00",
        "format_code-2379": "303"
    },
    {
        "segment_tag": "DTM",
        "function_code-2005": "164",
        "value-2380": "202412310830+00",
        "format_code-2379": "303"
    },
    {
        "segment_tag": "STS",
        "status_category_code-9015": "Z34",
        "status_reason_code-9013": "ZA4"
    },
    {
        "segment_tag": "QTY",
        "quantity_qualifier-6063": "220",
        "quantity_value-6060": "0,939",
        "quantity_unit-6411": null
    },
    {
        "segment_tag": "DTM",
        "function_code-2005": "163",
        "value-2380": "202412310830+00",
        "format_code-2379": "303"
    },
    {
        "segment_tag": "DTM",
        "function_code-2005": "164",
        "value-2380": "202412310845+00",
        "format_code-2379": "303"
    },
    {
        "segment_tag": "STS",
        "status_category_code-9015": "Z34",
        "status_reason_code-9013": "ZA4"
    },
    {
        "segment_tag": "QTY",
        "quantity_qualifier-6063": "220",
        "quantity_value-6060": "0,092",
        "quantity_unit-6411": null
    },
    {
        "segment_tag": "DTM",
        "function_code-2005": "163",
        "value-2380": "202412310845+00",
        "format_code-2379": "303"
    },
    {
        "segment_tag": "DTM",
        "function_code-2005": "164",
        "value-2380": "202412310900+00",
        "format_code-2379": "303"
    },
    {
        "segment_tag": "STS",
        "status_category_code-9015": "Z34",
        "status_reason_code-9013": "ZA4"
    },
    {
        "segment_tag": "QTY",
        "quantity_qualifier-6063": "220",
        "quantity_value-6060": "0,035",
        "quantity_unit-6411": null
    },
    {
        "segment_tag": "DTM",
        "function_code-2005": "163",
        "value-2380": "202412310900+00",
        "format_code-2379": "303"
    },
    {
        "segment_tag": "DTM",
        "function_code-2005": "164",
        "value-2380": "202412310915+00",
        "format_code-2379": "303"
    },
    {
        "segment_tag": "STS",
        "status_category_code-9015": "Z34",
        "status_reason_code-9013": "ZA4"
    },
    {
        "segment_tag": "QTY",
        "quantity_qualifier-6063": "220",
        "quantity_value-6060": "0,034",
        "quantity_unit-6411": null
    },
    {
        "segment_tag": "DTM",
        "function_code-2005": "163",
        "value-2380": "202412310915+00",
        "format_code-2379": "303"
    },
    {
        "segment_tag": "DTM",
        "function_code-2005": "164",
        "value-2380": "202412310930+00",
        "format_code-2379": "303"
    },
    {
        "segment_tag": "STS",
        "status_category_code-9015": "Z34",
        "status_reason_code-9013": "ZA4"
    },
    {
        "segment_tag": "QTY",
        "quantity_qualifier-6063": "220",
        "quantity_value-6060": "0,044",
        "quantity_unit-6411": null
    },
    {
        "segment_tag": "DTM",
        "function_code-2005": "163",
        "value-2380": "202412310930+00",
        "format_code-2379": "303"
    },
    {
        "segment_tag": "DTM",
        "function_code-2005": "164",
        "value-2380": "202412310945+00",
        "format_code-2379": "303"
    },
    {
        "segment_tag": "STS",
        "status_category_code-9015": "Z34",
        "status_reason_code-9013": "ZA4"
    },
    {
        "segment_tag": "QTY",
        "quantity_qualifier-6063": "220",
        "quantity_value-6060": "0,032",
        "quantity_unit-6411": null
    },
    {
        "segment_tag": "DTM",
        "function_code-2005": "163",
        "value-2380": "202412310945+00",
        "format_code-2379": "303"
    },
    {
        "segment_tag": "DTM",
        "function_code-2005": "164",
        "value-2380": "202412311000+00",
        "format_code-2379": "303"
    },
    {
        "segment_tag": "STS",
        "status_category_code-9015": "Z34",
        "status_reason_code-9013": "ZA4"
    },
    {
        "segment_tag": "QTY",
        "quantity_qualifier-6063": "220",
        "quantity_value-6060": "0,05",
        "quantity_unit-6411": null
    },
    {
        "segment_tag": "DTM",
        "function_code-2005": "163",
        "value-2380": "202412311000+00",
        "format_code-2379": "303"
    },
    {
        "segment_tag": "DTM",
        "function_code-2005": "164",
        "value-2380": "202412311015+00",
        "format_code-2379": "303"
    },
    {
        "segment_tag": "STS",
        "status_category_code-9015": "Z34",
        "status_reason_code-9013": "ZA4"
    },
    {
        "segment_tag": "QTY",
        "quantity_qualifier-6063": "220",
        "quantity_value-6060": "0,055",
        "quantity_unit-6411": null
    },
    {
        "segment_tag": "DTM",
        "function_code-2005": "163",
        "value-2380": "202412311015+00",
        "format_code-2379": "303"
    },
    {
        "segment_tag": "DTM",
        "function_code-2005": "164",
        "value-2380": "202412311030+00",
        "format_code-2379": "303"
    },
    {
        "segment_tag": "STS",
        "status_category_code-9015": "Z34",
        "status_reason_code-9013": "ZA4"
    },
    {
        "segment_tag": "QTY",
        "quantity_qualifier-6063": "220",
        "quantity_value-6060": "0,046",
        "quantity_unit-6411": null
    },
    {
        "segment_tag": "DTM",
        "function_code-2005": "163",
        "value-2380": "202412311030+00",
        "format_code-2379": "303"
    },
    {
        "segment_tag": "DTM",
        "function_code-2005": "164",
        "value-2380": "202412311045+00",
        "format_code-2379": "303"
    },
    {
        "segment_tag": "STS",
        "status_category_code-9015": "Z34",
        "status_reason_code-9013": "ZA4"
    },
    {
        "segment_tag": "QTY",
        "quantity_qualifier-6063": "220",
        "quantity_value-6060": "0,04",
        "quantity_unit-6411": null
    },
    {
        "segment_tag": "DTM",
        "function_code-2005": "163",
        "value-2380": "202412311045+00",
        "format_code-2379": "303"
    },
    {
        "segment_tag": "DTM",
        "function_code-2005": "164",
        "value-2380": "202412311100+00",
        "format_code-2379": "303"
    },
    {
        "segment_tag": "STS",
        "status_category_code-9015": "Z34",
        "status_reason_code-9013": "ZA4"
    },
    {
        "segment_tag": "QTY",
        "quantity_qualifier-6063": "220",
        "quantity_value-6060": "0,044",
        "quantity_unit-6411": null
    },
    {
        "segment_tag": "DTM",
        "function_code-2005": "163",
        "value-2380": "202412311100+00",
        "format_code-2379": "303"
    },
    {
        "segment_tag": "DTM",
        "function_code-2005": "164",
        "value-2380": "202412311115+00",
        "format_code-2379": "303"
    },
    {
        "segment_tag": "STS",
        "status_category_code-9015": "Z34",
        "status_reason_code-9013": "ZA4"
    },
    {
        "segment_tag": "QTY",
        "quantity_qualifier-6063": "220",
        "quantity_value-6060": "0,042",
        "quantity_unit-6411": null
    },
    {
        "segment_tag": "DTM",
        "function_code-2005": "163",
        "value-2380": "202412311115+00",
        "format_code-2379": "303"
    },
    {
        "segment_tag": "DTM",
        "function_code-2005": "164",
        "value-2380": "202412311130+00",
        "format_code-2379": "303"
    },
    {
        "segment_tag": "STS",
        "status_category_code-9015": "Z34",
        "status_reason_code-9013": "ZA4"
    },
    {
        "segment_tag": "QTY",
        "quantity_qualifier-6063": "220",
        "quantity_value-6060": "0,059",
        "quantity_unit-6411": null
    },
    {
        "segment_tag": "DTM",
        "function_code-2005": "163",
        "value-2380": "202412311130+00",
        "format_code-2379": "303"
    },
    {
        "segment_tag": "DTM",
        "function_code-2005": "164",
        "value-2380": "202412311145+00",
        "format_code-2379": "303"
    },
    {
        "segment_tag": "STS",
        "status_category_code-9015": "Z34",
        "status_reason_code-9013": "ZA4"
    },
    {
        "segment_tag": "QTY",
        "quantity_qualifier-6063": "220",
        "quantity_value-6060": "0,052",
        "quantity_unit-6411": null
    },
    {
        "segment_tag": "DTM",
        "function_code-2005": "163",
        "value-2380": "202412311145+00",
        "format_code-2379": "303"
    },
    {
        "segment_tag": "DTM",
        "function_code-2005": "164",
        "value-2380": "202412311200+00",
        "format_code-2379": "303"
    },
    {
        "segment_tag": "STS",
        "status_category_code-9015": "Z34",
        "status_reason_code-9013": "ZA4"
    },
    {
        "segment_tag": "QTY",
        "quantity_qualifier-6063": "220",
        "quantity_value-6060": "0,058",
        "quantity_unit-6411": null
    },
    {
        "segment_tag": "DTM",
        "function_code-2005": "163",
        "value-2380": "202412311200+00",
        "format_code-2379": "303"
    },
    {
        "segment_tag": "DTM",
        "function_code-2005": "164",
        "value-2380": "202412311215+00",
        "format_code-2379": "303"
    },
    {
        "segment_tag": "STS",
        "status_category_code-9015": "Z34",
        "status_reason_code-9013": "ZA4"
    },
    {
        "segment_tag": "QTY",
        "quantity_qualifier-6063": "220",
        "quantity_value-6060": "0,042",
        "quantity_unit-6411": null
    },
    {
        "segment_tag": "DTM",
        "function_code-2005": "163",
        "value-2380": "202412311215+00",
        "format_code-2379": "303"
    },
    {
        "segment_tag": "DTM",
        "function_code-2005": "164",
        "value-2380": "202412311230+00",
        "format_code-2379": "303"
    },
    {
        "segment_tag": "STS",
        "status_category_code-9015": "Z34",
        "status_reason_code-9013": "ZA4"
    },
    {
        "segment_tag": "QTY",
        "quantity_qualifier-6063": "220",
        "quantity_value-6060": "0,032",
        "quantity_unit-6411": null
    },
    {
        "segment_tag": "DTM",
        "function_code-2005": "163",
        "value-2380": "202412311230+00",
        "format_code-2379": "303"
    },
    {
        "segment_tag": "DTM",
        "function_code-2005": "164",
        "value-2380": "202412311245+00",
        "format_code-2379": "303"
    },
    {
        "segment_tag": "STS",
        "status_category_code-9015": "Z34",
        "status_reason_code-9013": "ZA4"
    },
    {
        "segment_tag": "QTY",
        "quantity_qualifier-6063": "220",
        "quantity_value-6060": "0,044",
        "quantity_unit-6411": null
    },
    {
        "segment_tag": "DTM",
        "function_code-2005": "163",
        "value-2380": "202412311245+00",
        "format_code-2379": "303"
    },
    {
        "segment_tag": "DTM",
        "function_code-2005": "164",
        "value-2380": "202412311300+00",
        "format_code-2379": "303"
    },
    {
        "segment_tag": "STS",
        "status_category_code-9015": "Z34",
        "status_reason_code-9013": "ZA4"
    },
    {
        "segment_tag": "QTY",
        "quantity_qualifier-6063": "220",
        "quantity_value-6060": "0,054",
        "quantity_unit-6411": null
    },
    {
        "segment_tag": "DTM",
        "function_code-2005": "163",
        "value-2380": "202412311300+00",
        "format_code-2379": "303"
    },
    {
        "segment_tag": "DTM",
        "function_code-2005": "164",
        "value-2380": "202412311315+00",
        "format_code-2379": "303"
    },
    {
        "segment_tag": "STS",
        "status_category_code-9015": "Z34",
        "status_reason_code-9013": "ZA4"
    },
    {
        "segment_tag": "QTY",
        "quantity_qualifier-6063": "220",
        "quantity_value-6060": "0,077",
        "quantity_unit-6411": null
    },
    {
        "segment_tag": "DTM",
        "function_code-2005": "163",
        "value-2380": "202412311315+00",
        "format_code-2379": "303"
    },
    {
        "segment_tag": "DTM",
        "function_code-2005": "164",
        "value-2380": "202412311330+00",
        "format_code-2379": "303"
    },
    {
        "segment_tag": "STS",
        "status_category_code-9015": "Z34",
        "status_reason_code-9013": "ZA4"
    },
    {
        "segment_tag": "QTY",
        "quantity_qualifier-6063": "220",
        "quantity_value-6060": "0,052",
        "quantity_unit-6411": null
    },
    {
        "segment_tag": "DTM",
        "function_code-2005": "163",
        "value-2380": "202412311330+00",
        "format_code-2379": "303"
    },
    {
        "segment_tag": "DTM",
        "function_code-2005": "164",
        "value-2380": "202412311345+00",
        "format_code-2379": "303"
    },
    {
        "segment_tag": "STS",
        "status_category_code-9015": "Z34",
        "status_reason_code-9013": "ZA4"
    },
    {
        "segment_tag": "QTY",
        "quantity_qualifier-6063": "220",
        "quantity_value-6060": "0,043",
        "quantity_unit-6411": null
    },
    {
        "segment_tag": "DTM",
        "function_code-2005": "163",
        "value-2380": "202412311345+00",
        "format_code-2379": "303"
    },
    {
        "segment_tag": "DTM",
        "function_code-2005": "164",
        "value-2380": "202412311400+00",
        "format_code-2379": "303"
    },
    {
        "segment_tag": "STS",
        "status_category_code-9015": "Z34",
        "status_reason_code-9013": "ZA4"
    },
    {
        "segment_tag": "QTY",
        "quantity_qualifier-6063": "220",
        "quantity_value-6060": "0,039",
        "quantity_unit-6411": null
    },
    {
        "segment_tag": "DTM",
        "function_code-2005": "163",
        "value-2380": "202412311400+00",
        "format_code-2379": "303"
    },
    {
        "segment_tag": "DTM",
        "function_code-2005": "164",
        "value-2380": "202412311415+00",
        "format_code-2379": "303"
    },
    {
        "segment_tag": "STS",
        "status_category_code-9015": "Z34",
        "status_reason_code-9013": "ZA4"
    },
    {
        "segment_tag": "QTY",
        "quantity_qualifier-6063": "220",
        "quantity_value-6060": "0,045",
        "quantity_unit-6411": null
    },
    {
        "segment_tag": "DTM",
        "function_code-2005": "163",
        "value-2380": "202412311415+00",
        "format_code-2379": "303"
    },
    {
        "segment_tag": "DTM",
        "function_code-2005": "164",
        "value-2380": "202412311430+00",
        "format_code-2379": "303"
    },
    {
        "segment_tag": "STS",
        "status_category_code-9015": "Z34",
        "status_reason_code-9013": "ZA4"
    },
    {
        "segment_tag": "QTY",
        "quantity_qualifier-6063": "220",
        "quantity_value-6060": "0,034",
        "quantity_unit-6411": null
    },
    {
        "segment_tag": "DTM",
        "function_code-2005": "163",
        "value-2380": "202412311430+00",
        "format_code-2379": "303"
    },
    {
        "segment_tag": "DTM",
        "function_code-2005": "164",
        "value-2380": "202412311445+00",
        "format_code-2379": "303"
    },
    {
        "segment_tag": "STS",
        "status_category_code-9015": "Z34",
        "status_reason_code-9013": "ZA4"
    },
    {
        "segment_tag": "QTY",
        "quantity_qualifier-6063": "67",
        "quantity_value-6060": "0,021",
        "quantity_unit-6411": null
    },
    {
        "segment_tag": "DTM",
        "function_code-2005": "163",
        "value-2380": "202412311445+00",
        "format_code-2379": "303"
    },
    {
        "segment_tag": "DTM",
        "function_code-2005": "164",
        "value-2380": "202412311500+00",
        "format_code-2379": "303"
    },
    {
        "segment_tag": "STS",
        "status_category_code-9015": "Z32",
        "status_reason_code-9013": "ZJ2"
    },
    {
        "segment_tag": "STS",
        "status_category_code-9015": "Z34",
        "status_reason_code-9013": "ZB0"
    },
    {
        "segment_tag": "STS",
        "status_category_code-9015": "Z40",
        "status_reason_code-9013": "ZB0"
    },
    {
        "segment_tag": "QTY",
        "quantity_qualifier-6063": "67",
        "quantity_value-6060": "0,021",
        "quantity_unit-6411": null
    },
    {
        "segment_tag": "DTM",
        "function_code-2005": "163",
        "value-2380": "202412311500+00",
        "format_code-2379": "303"
    },
    {
        "segment_tag": "DTM",
        "function_code-2005": "164",
        "value-2380": "202412311515+00",
        "format_code-2379": "303"
    },
    {
        "segment_tag": "STS",
        "status_category_code-9015": "Z32",
        "status_reason_code-9013": "ZJ2"
    },
    {
        "segment_tag": "STS",
        "status_category_code-9015": "Z34",
        "status_reason_code-9013": "ZB0"
    },
    {
        "segment_tag": "STS",
        "status_category_code-9015": "Z40",
        "status_reason_code-9013": "ZB0"
    },
    {
        "segment_tag": "QTY",
        "quantity_qualifier-6063": "220",
        "quantity_value-6060": "0,011",
        "quantity_unit-6411": null
    },
    {
        "segment_tag": "DTM",
        "function_code-2005": "163",
        "value-2380": "202412311515+00",
        "format_code-2379": "303"
    },
    {
        "segment_tag": "DTM",
        "function_code-2005": "164",
        "value-2380": "202412311530+00",
        "format_code-2379": "303"
    },
    {
        "segment_tag": "STS",
        "status_category_code-9015": "Z34",
        "status_reason_code-9013": "ZA4"
    },
    {
        "segment_tag": "QTY",
        "quantity_qualifier-6063": "220",
        "quantity_value-6060": "0,015",
        "quantity_unit-6411": null
    },
    {
        "segment_tag": "DTM",
        "function_code-2005": "163",
        "value-2380": "202412311530+00",
        "format_code-2379": "303"
    },
    {
        "segment_tag": "DTM",
        "function_code-2005": "164",
        "value-2380": "202412311545+00",
        "format_code-2379": "303"
    },
    {
        "segment_tag": "STS",
        "status_category_code-9015": "Z34",
        "status_reason_code-9013": "ZA4"
    },
    {
        "segment_tag": "QTY",
        "quantity_qualifier-6063": "220",
        "quantity_value-6060": "0,014",
        "quantity_unit-6411": null
    },
    {
        "segment_tag": "DTM",
        "function_code-2005": "163",
        "value-2380": "202412311545+00",
        "format_code-2379": "303"
    },
    {
        "segment_tag": "DTM",
        "function_code-2005": "164",
        "value-2380": "202412311600+00",
        "format_code-2379": "303"
    },
    {
        "segment_tag": "STS",
        "status_category_code-9015": "Z34",
        "status_reason_code-9013": "ZA4"
    },
    {
        "segment_tag": "QTY",
        "quantity_qualifier-6063": "220",
        "quantity_value-6060": "0,008",
        "quantity_unit-6411": null
    },
    {
        "segment_tag": "DTM",
        "function_code-2005": "163",
        "value-2380": "202412311600+00",
        "format_code-2379": "303"
    },
    {
        "segment_tag": "DTM",
        "function_code-2005": "164",
        "value-2380": "202412311615+00",
        "format_code-2379": "303"
    },
    {
        "segment_tag": "STS",
        "status_category_code-9015": "Z34",
        "status_reason_code-9013": "ZA4"
    },
    {
        "segment_tag": "QTY",
        "quantity_qualifier-6063": "220",
        "quantity_value-6060": "0,007",
        "quantity_unit-6411": null
    },
    {
        "segment_tag": "DTM",
        "function_code-2005": "163",
        "value-2380": "202412311615+00",
        "format_code-2379": "303"
    },
    {
        "segment_tag": "DTM",
        "function_code-2005": "164",
        "value-2380": "202412311630+00",
        "format_code-2379": "303"
    },
    {
        "segment_tag": "STS",
        "status_category_code-9015": "Z34",
        "status_reason_code-9013": "ZA4"
    },
    {
        "segment_tag": "QTY",
        "quantity_qualifier-6063": "220",
        "quantity_value-6060": "0,008",
        "quantity_unit-6411": null
    },
    {
        "segment_tag": "DTM",
        "function_code-2005": "163",
        "value-2380": "202412311630+00",
        "format_code-2379": "303"
    },
    {
        "segment_tag": "DTM",
        "function_code-2005": "164",
        "value-2380": "202412311645+00",
        "format_code-2379": "303"
    },
    {
        "segment_tag": "STS",
        "status_category_code-9015": "Z34",
        "status_reason_code-9013": "ZA4"
    },
    {
        "segment_tag": "QTY",
        "quantity_qualifier-6063": "220",
        "quantity_value-6060": "0,004",
        "quantity_unit-6411": null
    },
    {
        "segment_tag": "DTM",
        "function_code-2005": "163",
        "value-2380": "202412311645+00",
        "format_code-2379": "303"
    },
    {
        "segment_tag": "DTM",
        "function_code-2005": "164",
        "value-2380": "202412311700+00",
        "format_code-2379": "303"
    },
    {
        "segment_tag": "STS",
        "status_category_code-9015": "Z34",
        "status_reason_code-9013": "ZA4"
    },
    {
        "segment_tag": "QTY",
        "quantity_qualifier-6063": "220",
        "quantity_value-6060": "0,004",
        "quantity_unit-6411": null
    },
    {
        "segment_tag": "DTM",
        "function_code-2005": "163",
        "value-2380": "202412311700+00",
        "format_code-2379": "303"
    },
    {
        "segment_tag": "DTM",
        "function_code-2005": "164",
        "value-2380": "202412311715+00",
        "format_code-2379": "303"
    },
    {
        "segment_tag": "STS",
        "status_category_code-9015": "Z34",
        "status_reason_code-9013": "ZA4"
    },
    {
        "segment_tag": "QTY",
        "quantity_qualifier-6063": "220",
        "quantity_value-6060": "0,09",
        "quantity_unit-6411": null
    },
    {
        "segment_tag": "DTM",
        "function_code-2005": "163",
        "value-2380": "202412311715+00",
        "format_code-2379": "303"
    },
    {
        "segment_tag": "DTM",
        "function_code-2005": "164",
        "value-2380": "202412311730+00",
        "format_code-2379": "303"
    },
    {
        "segment_tag": "STS",
        "status_category_code-9015": "Z34",
        "status_reason_code-9013": "ZA4"
    },
    {
        "segment_tag": "QTY",
        "quantity_qualifier-6063": "220",
        "quantity_value-6060": "0,103",
        "quantity_unit-6411": null
    },
    {
        "segment_tag": "DTM",
        "function_code-2005": "163",
        "value-2380": "202412311730+00",
        "format_code-2379": "303"
    },
    {
        "segment_tag": "DTM",
        "function_code-2005": "164",
        "value-2380": "202412311745+00",
        "format_code-2379": "303"
    },
    {
        "segment_tag": "STS",
        "status_category_code-9015": "Z34",
        "status_reason_code-9013": "ZA4"
    },
    {
        "segment_tag": "QTY",
        "quantity_qualifier-6063": "220",
        "quantity_value-6060": "0,428",
        "quantity_unit-6411": null
    },
    {
        "segment_tag": "DTM",
        "function_code-2005": "163",
        "value-2380": "202412311745+00",
        "format_code-2379": "303"
    },
    {
        "segment_tag": "DTM",
        "function_code-2005": "164",
        "value-2380": "202412311800+00",
        "format_code-2379": "303"
    },
    {
        "segment_tag": "STS",
        "status_category_code-9015": "Z34",
        "status_reason_code-9013": "ZA4"
    },
    {
        "segment_tag": "QTY",
        "quantity_qualifier-6063": "220",
        "quantity_value-6060": "0,45",
        "quantity_unit-6411": null
    },
    {
        "segment_tag": "DTM",
        "function_code-2005": "163",
        "value-2380": "202412311800+00",
        "format_code-2379": "303"
    },
    {
        "segment_tag": "DTM",
        "function_code-2005": "164",
        "value-2380": "202412311815+00",
        "format_code-2379": "303"
    },
    {
        "segment_tag": "STS",
        "status_category_code-9015": "Z34",
        "status_reason_code-9013": "ZA4"
    },
    {
        "segment_tag": "QTY",
        "quantity_qualifier-6063": "220",
        "quantity_value-6060": "2,526",
        "quantity_unit-6411": null
    },
    {
        "segment_tag": "DTM",
        "function_code-2005": "163",
        "value-2380": "202412311815+00",
        "format_code-2379": "303"
    },
    {
        "segment_tag": "DTM",
        "function_code-2005": "164",
        "value-2380": "202412311830+00",
        "format_code-2379": "303"
    },
    {
        "segment_tag": "STS",
        "status_category_code-9015": "Z34",
        "status_reason_code-9013": "ZA4"
    },
    {
        "segment_tag": "QTY",
        "quantity_qualifier-6063": "220",
        "quantity_value-6060": "3,066",
        "quantity_unit-6411": null
    },
    {
        "segment_tag": "DTM",
        "function_code-2005": "163",
        "value-2380": "202412311830+00",
        "format_code-2379": "303"
    },
    {
        "segment_tag": "DTM",
        "function_code-2005": "164",
        "value-2380": "202412311845+00",
        "format_code-2379": "303"
    },
    {
        "segment_tag": "STS",
        "status_category_code-9015": "Z34",
        "status_reason_code-9013": "ZA4"
    },
    {
        "segment_tag": "QTY",
        "quantity_qualifier-6063": "220",
        "quantity_value-6060": "3,545",
        "quantity_unit-6411": null
    },
    {
        "segment_tag": "DTM",
        "function_code-2005": "163",
        "value-2380": "202412311845+00",
        "format_code-2379": "303"
    },
    {
        "segment_tag": "DTM",
        "function_code-2005": "164",
        "value-2380": "202412311900+00",
        "format_code-2379": "303"
    },
    {
        "segment_tag": "STS",
        "status_category_code-9015": "Z34",
        "status_reason_code-9013": "ZA4"
    },
    {
        "segment_tag": "QTY",
        "quantity_qualifier-6063": "220",
        "quantity_value-6060": "2,23",
        "quantity_unit-6411": null
    },
    {
        "segment_tag": "DTM",
        "function_code-2005": "163",
        "value-2380": "202412311900+00",
        "format_code-2379": "303"
    },
    {
        "segment_tag": "DTM",
        "function_code-2005": "164",
        "value-2380": "202412311915+00",
        "format_code-2379": "303"
    },
    {
        "segment_tag": "STS",
        "status_category_code-9015": "Z34",
        "status_reason_code-9013": "ZA4"
    },
    {
        "segment_tag": "QTY",
        "quantity_qualifier-6063": "220",
        "quantity_value-6060": "2,147",
        "quantity_unit-6411": null
    },
    {
        "segment_tag": "DTM",
        "function_code-2005": "163",
        "value-2380": "202412311915+00",
        "format_code-2379": "303"
    },
    {
        "segment_tag": "DTM",
        "function_code-2005": "164",
        "value-2380": "202412311930+00",
        "format_code-2379": "303"
    },
    {
        "segment_tag": "STS",
        "status_category_code-9015": "Z34",
        "status_reason_code-9013": "ZA4"
    },
    {
        "segment_tag": "QTY",
        "quantity_qualifier-6063": "220",
        "quantity_value-6060": "2,893",
        "quantity_unit-6411": null
    },
    {
        "segment_tag": "DTM",
        "function_code-2005": "163",
        "value-2380": "202412311930+00",
        "format_code-2379": "303"
    },
    {
        "segment_tag": "DTM",
        "function_code-2005": "164",
        "value-2380": "202412311945+00",
        "format_code-2379": "303"
    },
    {
        "segment_tag": "STS",
        "status_category_code-9015": "Z34",
        "status_reason_code-9013": "ZA4"
    },
    {
        "segment_tag": "QTY",
        "quantity_qualifier-6063": "220",
        "quantity_value-6060": "2,503",
        "quantity_unit-6411": null
    },
    {
        "segment_tag": "DTM",
        "function_code-2005": "163",
        "value-2380": "202412311945+00",
        "format_code-2379": "303"
    },
    {
        "segment_tag": "DTM",
        "function_code-2005": "164",
        "value-2380": "202412312000+00",
        "format_code-2379": "303"
    },
    {
        "segment_tag": "STS",
        "status_category_code-9015": "Z34",
        "status_reason_code-9013": "ZA4"
    },
    {
        "segment_tag": "QTY",
        "quantity_qualifier-6063": "220",
        "quantity_value-6060": "3,551",
        "quantity_unit-6411": null
    },
    {
        "segment_tag": "DTM",
        "function_code-2005": "163",
        "value-2380": "202412312000+00",
        "format_code-2379": "303"
    },
    {
        "segment_tag": "DTM",
        "function_code-2005": "164",
        "value-2380": "202412312015+00",
        "format_code-2379": "303"
    },
    {
        "segment_tag": "STS",
        "status_category_code-9015": "Z34",
        "status_reason_code-9013": "ZA4"
    },
    {
        "segment_tag": "QTY",
        "quantity_qualifier-6063": "220",
        "quantity_value-6060": "3,759",
        "quantity_unit-6411": null
    },
    {
        "segment_tag": "DTM",
        "function_code-2005": "163",
        "value-2380": "202412312015+00",
        "format_code-2379": "303"
    },
    {
        "segment_tag": "DTM",
        "function_code-2005": "164",
        "value-2380": "202412312030+00",
        "format_code-2379": "303"
    },
    {
        "segment_tag": "STS",
        "status_category_code-9015": "Z34",
        "status_reason_code-9013": "ZA4"
    },
    {
        "segment_tag": "QTY",
        "quantity_qualifier-6063": "220",
        "quantity_value-6060": "4,108",
        "quantity_unit-6411": null
    },
    {
        "segment_tag": "DTM",
        "function_code-2005": "163",
        "value-2380": "202412312030+00",
        "format_code-2379": "303"
    },
    {
        "segment_tag": "DTM",
        "function_code-2005": "164",
        "value-2380": "202412312045+00",
        "format_code-2379": "303"
    },
    {
        "segment_tag": "STS",
        "status_category_code-9015": "Z34",
        "status_reason_code-9013": "ZA4"
    },
    {
        "segment_tag": "QTY",
        "quantity_qualifier-6063": "220",
        "quantity_value-6060": "3,93",
        "quantity_unit-6411": null
    },
    {
        "segment_tag": "DTM",
        "function_code-2005": "163",
        "value-2380": "202412312045+00",
        "format_code-2379": "303"
    },
    {
        "segment_tag": "DTM",
        "function_code-2005": "164",
        "value-2380": "202412312100+00",
        "format_code-2379": "303"
    },
    {
        "segment_tag": "STS",
        "status_category_code-9015": "Z34",
        "status_reason_code-9013": "ZA4"
    },
    {
        "segment_tag": "QTY",
        "quantity_qualifier-6063": "220",
        "quantity_value-6060": "3,344",
        "quantity_unit-6411": null
    },
    {
        "segment_tag": "DTM",
        "function_code-2005": "163",
        "value-2380": "202412312100+00",
        "format_code-2379": "303"
    },
    {
        "segment_tag": "DTM",
        "function_code-2005": "164",
        "value-2380": "202412312115+00",
        "format_code-2379": "303"
    },
    {
        "segment_tag": "STS",
        "status_category_code-9015": "Z34",
        "status_reason_code-9013": "ZA4"
    },
    {
        "segment_tag": "QTY",
        "quantity_qualifier-6063": "220",
        "quantity_value-6060": "3,952",
        "quantity_unit-6411": null
    },
    {
        "segment_tag": "DTM",
        "function_code-2005": "163",
        "value-2380": "202412312115+00",
        "format_code-2379": "303"
    },
    {
        "segment_tag": "DTM",
        "function_code-2005": "164",
        "value-2380": "202412312130+00",
        "format_code-2379": "303"
    },
    {
        "segment_tag": "STS",
        "status_category_code-9015": "Z34",
        "status_reason_code-9013": "ZA4"
    },
    {
        "segment_tag": "QTY",
        "quantity_qualifier-6063": "220",
        "quantity_value-6060": "4,192",
        "quantity_unit-6411": null
    },
    {
        "segment_tag": "DTM",
        "function_code-2005": "163",
        "value-2380": "202412312130+00",
        "format_code-2379": "303"
    },
    {
        "segment_tag": "DTM",
        "function_code-2005": "164",
        "value-2380": "202412312145+00",
        "format_code-2379": "303"
    },
    {
        "segment_tag": "STS",
        "status_category_code-9015": "Z34",
        "status_reason_code-9013": "ZA4"
    },
    {
        "segment_tag": "QTY",
        "quantity_qualifier-6063": "220",
        "quantity_value-6060": "4,504",
        "quantity_unit-6411": null
    },
    {
        "segment_tag": "DTM",
        "function_code-2005": "163",
        "value-2380": "202412312145+00",
        "format_code-2379": "303"
    },
    {
        "segment_tag": "DTM",
        "function_code-2005": "164",
        "value-2380": "202412312200+00",
        "format_code-2379": "303"
    },
    {
        "segment_tag": "STS",
        "status_category_code-9015": "Z34",
        "status_reason_code-9013": "ZA4"
    },
    {
        "segment_tag": "QTY",
        "quantity_qualifier-6063": "220",
        "quantity_value-6060": "4,427",
        "quantity_unit-6411": null
    },
    {
        "segment_tag": "DTM",
        "function_code-2005": "163",
        "value-2380": "202412312200+00",
        "format_code-2379": "303"
    },
    {
        "segment_tag": "DTM",
        "function_code-2005": "164",
        "value-2380": "202412312215+00",
        "format_code-2379": "303"
    },
    {
        "segment_tag": "STS",
        "status_category_code-9015": "Z34",
        "status_reason_code-9013": "ZA4"
    },
    {
        "segment_tag": "QTY",
        "quantity_qualifier-6063": "220",
        "quantity_value-6060": "2,84",
        "quantity_unit-6411": null
    },
    {
        "segment_tag": "DTM",
        "function_code-2005": "163",
        "value-2380": "202412312215+00",
        "format_code-2379": "303"
    },
    {
        "segment_tag": "DTM",
        "function_code-2005": "164",
        "value-2380": "202412312230+00",
        "format_code-2379": "303"
    },
    {
        "segment_tag": "STS",
        "status_category_code-9015": "Z34",
        "status_reason_code-9013": "ZA4"
    },
    {
        "segment_tag": "QTY",
        "quantity_qualifier-6063": "220",
        "quantity_value-6060": "2,173",
        "quantity_unit-6411": null
    },
    {
        "segment_tag": "DTM",
        "function_code-2005": "163",
        "value-2380": "202412312230+00",
        "format_code-2379": "303"
    },
    {
        "segment_tag": "DTM",
        "function_code-2005": "164",
        "value-2380": "202412312245+00",
        "format_code-2379": "303"
    },
    {
        "segment_tag": "STS",
        "status_category_code-9015": "Z34",
        "status_reason_code-9013": "ZA4"
    },
    {
        "segment_tag": "QTY",
        "quantity_qualifier-6063": "220",
        "quantity_value-6060": "1,921",
        "quantity_unit-6411": null
    },
    {
        "segment_tag": "DTM",
        "function_code-2005": "163",
        "value-2380": "202412312245+00",
        "format_code-2379": "303"
    },
    {
        "segment_tag": "DTM",
        "function_code-2005": "164",
        "value-2380": "202412312300+00",
        "format_code-2379": "303"
    },
    {
        "segment_tag": "STS",
        "status_category_code-9015": "Z34",
        "status_reason_code-9013": "ZA4"
    },
    {
        "segment_tag": "UNT",
        "number_of_segments-0074": "406",
        "message_reference_number-0062": "1"
    },
    {
        "segment_tag": "UNZ",
        "interchange_control_count-0036": "1",
        "interchange_control_reference-0020": "CS0000000GAZ6Y"
    }
]